{"id":"1c9c766f-f271-4d2d-82e1-65817880ff7d","key":"04","link":"https://indra.ai/rigveda/books/04.html","hymns":[{"id":"60d58192-ab0f-424a-a1b3-c5273bafa33f","key":"04001","book":"04","title":"HYMN I. Agni.","link":"https://indra.ai/rigveda/hymns/04001.html","text":"p: , THEE @Agni, have the #Devas, ever of one accord, sent hither down, a @Deva, appointed messenger, yea, with their wisdom sent thee down. The #Immortal, O thou Holy One, mid mortal #men, the devoted @Deva, the #wise, have they brought forth, brought forth the omnipresent devoted #Sage.\n\np: As such, O @Agni, bring with favour to the #Devas thy #Brother @Varuna who loveth #offering, True to the Law, the Aditya who supporteth #men, the #King, supporter of #mankind.\n\np: Do thou, O #Friend, turn hither him who is our #Friend, swift as a wheel, like two #car-#steeds in rapid course, Wondrous! to us in rapid course. O @Agni, find thou grace for us with @Varuna, with #Maruts who illumine all. Bless us, thou Radiant One, for seed and #progeny, yea, bless us, O thou Wondrous @Deva.\n\np: Do thou who knowest @Varuna, O @Agni, put far away from us the @Deva's displeasure. Best Offerer, brightest One, refulgent remove thou far from us all those who hate us.\n\np: Be thou, O @Agni, nearest us with assist, our closest #Friend while now this Morn is breaking. Reconcile to us @Varuna, be bounteous enjoy the gracious #juice; be swift to hear us.\n\np: #Excellent is the glance, of brightest #splendour, which the auspicious @Deva.bestows on mortals- The @Deva's glance, longed-for even as the butter, pure, heated, of the #cow, the #MilchCow's bounty.\n\np: Three are those births, the true, the most exalted, eagerly longed-for, of the @Deva, of @Agni. He came invested in the boundless region, pure, radiant, friendly, mightily resplendent.\n\np: This envoy joyeth in all seats of #worship, borne on his golden #car, sweet-tongued Invoker: Lovely to look on, with red #steeds, effulgent, like a feast rich in #food, joyous forever.\n\np: Allied by #worship, let him give #man knowledge: by an extended cord they lead him onward. He stays, effectual in this mortal's dwelling, and the @Deva.wins a share in his possessions.\n\np: Let @Agni -for he knows the way- conduct us to all that he enjoys of @Deva.sent #riches, what all the Immortals have prepared with wisdom, #Dyaus, Sire, begetter, raining down true blessings.\n\np: In houses first he sprang into existence, at great $Heaven's base, and in this region's bosom; Footless and headless, both his ends concealing, in his Bull's lair drawing himself together.\n\np: Wondrously first he rose aloft, defiant, in the Bull's lair, the homeof holy #Order, Longed-for, young, beautiful, and far-resplendent: and sevendear frieuds sprang up unto the #Mighty.\n\np: Here did our #human #fathers take their places, fain to fulfil the sacred Law of #worship. Forth drave they, with loud #call, @Dawn's teeming Milch-kine bid in the mountainstable, in the cavern.\n\np: Splendid were they when they had rent the mountain: others, around, shall tell forth this their exploit. They sang their #song, prepared to free the #cattle: they found the #light; with holy hymns they worshipped.\n\np: Eager, with thought intent upon the booty, the #men with their celestial speech threw open, the solid mountain firm, compact, enclosing, confining Cows, the stable full of #cattle.\n\np: The Milch-#cow's earliest name they comprehended: they found the #Mother's thrice-seven noblest titles. This the bands knew, and sent forth acclamation:with the Bull's sheen the Red One was apparent.\n\np: The turbid darkness fled, the $Heaven was sp, endid! up rose the bright beam of celestial #Morning. @Surya ascended to the wide expanses, beholding deeds of #men both good and evil.\n\np: Then, afterwards they looked around, awakened, when first they held that $Heaven allotted #treasure.. Now all the #Devas abide in all their dwellings. @Varuna, @Mitra, be the prayer effective.\n\np: I will #call hither brightly-beaming @Agni, the Herald, all-supporting, best at #worship. He hath disclosed, like the milch cows' pure udder, the Sorria's #juice when cleansed and poured from beakers.\n\np: The freest @Deva.of all who should be worshipped, the guest who is received in all #men's houses, @Agni who hath secured the #Devas’ high favour.may he be gracious, to us #Jatavedas.","people":["@Agni","@Mitra","@Varuna","@Deva","@Surya","@Dawn"],"places":["$Heaven"],"things":["#Worship","#Mankind","#Steeds","#Mankind","#Offering","#Light","#Treasure","#Food","#Men","#Juice","#Song","#Wise","#Mighty","#Car","#Splendour","#Excellent","#Worship","#Offering","#Friend","#King","#Sage","#Cow","#call","#Riches","#Order","#Morning","#Cattle","#MilchCow"],"groups":["#Devas","#Dyaus","#Maruts","#Jatavedas","#Fathers","#Human","#Mother","#Brother","#Immortal","#Progeny","#Man"],"concepts":["Celestial","Good","Evil","Beautiful","Blessings","Immortal","Holy","Sacred","Wisdom","Offering","Worshipped","Auspicious","Swift"],"hash":"md5-qc7DOEWsEyEvoLhI289Pfg==","created":"Wednesday, November 22, 2023 - 6:01:41 AM"},{"id":"def20e41-3b58-475f-afd0-3f78ceacfec1","key":"04002","book":"04","title":"HYMN II. Agni.","link":"https://indra.ai/rigveda/hymns/04002.html","text":"p: THE, Faithful One, #Immortal among mortals, a @Deva among the #Devas, appointed envoy, Monk, best at #worship, must #shine forth in #glory . @Agni shall be raised high with #man's oblations.\n\np: #Born for us here this day, O #Son of Vigour, between both races of #born beings, @Agni, Thou farest as an envoy, having harnessed, Sublime One! thy #strong-muscled radiant stallions.\n\np: I laud the ruddy #steeds who pour down #blessing, dropping oil, flectest through the thoualit of #Order. Yoking red #horses to and fro thou goest between you #Deities and mortal races.\n\np: @Aryaman, @Mitra, @Varuna, and @Indra with @Visnu, of the #Devas, #Maruts and @Asvins- These, @Agni, with good #car and #steeds, bring hither, most bountiful, to folk with fair oblations.\n\np: @Agni, be this  'our #offering eternal, with #brave #friends, rich in kine and sheep and #horses, Rich, #Asura! in sacred #food and children, in full assembly, #wealth broad-based and during.\n\np: The #man who, sweating, brings for thee the fuel, and makes his head to ache, thy faithful servant. @Agni, to him be a self-#strong Protector guard him from all who seek to do him mischief.\n\np: Who brings thee #food, though thou hast #food in plenty, welcomes his cheerful guest and speeds him onward, who kindles thee devoutly in his dwelling,to him be #wealth secure and freely giving.\n\np: Whoso sings #praise to thee at eve or #morning, and, with oblation, doth the thing thou lovest. In his own #home, even as a goId-girt courser, rescue him from distress, the bounteous giver.\n\np: Whoso brings #gifts to thee #Immortal, @Agni, and doth thee service with uplifted ladle. Let him not, sorely toiling, lose his #riches; let not the sinner's wickedness enclose him.\n\np: Whose well-wrought #worship thou acceptest, @Agni, thou @Deva a mortal's #gift, thou liberal Giver. Dear be his #offering to thee, most Youthful! an. May we strengthen him when he adores thee.\n\np: May he who knows distinguish sense and folly of #men, like straight and crooked backs of #horses. Lead us, O @Deva, to #wealth and noble #offspring: keep penury afar and grant us plenty.\n\np: This #Sage the Sages, ne’er deceived, commanded, setting him down in dwellings of the living. Henc. Mayst thou, friendly @Deva, with rapid footsteps behold the #Devas, wonderful, fair to look on.\n\np: Good guidance hast thou for the priest, O @Agni, who, Youngest @Deva. with outpoured #Soma serves thee. Ruler of #men, thou joyous @Deva, bring #treasure. splendid and plentiful to aid the toiler.\n\np: Now all that we, thy faithful servants, @Agni, have done with feet, with hands, and with our bodies, the #wise, with toil, the holy rite have guided, as those who frame a #car with manual cunning.\n\np: May we, seven sages first in rank, engender, from @Dawn the #Mother, #men to be ordainers. May we, #Angirases, be #sons of $Heaven, and, radiant, burst the #wealth-containing mountain.\n\np: As in the days of old our ancient #Fathers, speeding the #work of holy #worship, @Agni, Sought pure #light and devotion, singing praises; they cleft the ground and made red #Dawns apparent.\n\np: #Devas, doing holy acts, devout, resplendent, smelting like ore their #human generations. Enkindling @Agni and exalting @Indra, they came encompassing the stall of #cattle.\n\np: #Strong One! he marked them-and the #Devas before them-like herds of #cattle in a foodful pasture. There they moaned forth their #strong desire for mortals, to aid the True, the nearest One, the Living.\n\np: We have worked for thee, we have laboured nobly-bright #Dawns have shed their #light upon our #worship- Adding a #beauty to the perfect @Agni, and the @Deva's beauteous eye that shines forever.\n\np: @Agni, Disposer, we have sung these praises to thee the #Wise: do thou accept them gladly. Blaze up on high and ever make us richer. Give us great #wealth, O thou whose boons are many.","people":["@Indra","@Agni","@Visnu","@Mitra","@Varuna","@Asvins","@Visnu","@Deva","@Dawn","@Aryaman"],"places":["$Heaven"],"things":["#Worship","#Steeds","#Work","#Born","#Soma","#Glory","#Offering","#Shine","#Light","#Treasure","#Wealth","#Food","#Men","#Beauty","#Home","#Wise","#Offspring","#Strong","#Car","#Blessing","#Praise","#Brave","#Gift","#Worship","#Blessing","#Offering","#Friends","#Sage","#Horses","#Riches","#Order","#Morning","#Cattle","#Gifts"],"groups":["#Devas","#Asura","#Maruts","#Fathers","#Sons","#Deities","#Dawns","#Human","#Mother","#Son","#Immortal","#Angirases","#Man"],"concepts":["Good","Immortal","Holy","Sacred","Devout","Offering","Giver","Noble"],"hash":"md5-tmVTq+Bgne9+euXLZwrYPw==","created":"Wednesday, November 22, 2023 - 6:01:41 AM"},{"id":"b6cdd7d7-a83e-4a46-babc-c7daa5470b57","key":"04003","book":"04","title":"HYMN III. Agni.","link":"https://indra.ai/rigveda/hymns/04003.html","text":"p: WIN, to assist you, Rudra, #Lord of #worship, Monk of both worlds, effectual Offerer, @Agni, invested with his golden colours, before the thunder strike and lay you senseless.\n\np: This shrine have we made ready for thy coming, as the fond dame attires her for her #husband. Performer of good #work, sit down before us, invested while these flames incline to meet thee.\n\np: A #hymn, O Monk, to him who hears, the gentle, to him who looks on #men, exceeding gracious, a #song of #praise sing to the @Deva.#Immortal, whom the stone, presser of the sweet #juice, worships.\n\np: Even as true knower of the Law, O @Agni, to this our solemn rite he thou attentive. When shall thy #songs of festival be sung thee? When is thy friendship shown within our dwelling?\n\np: Why this complaint to @Varuna, O @Agni? And why to $Heaven? for what is our transgression? How wilt thou speak to $Earth and bounteous @Mitra? What wilt thou say to @Aryaman and @Bhaga?\n\np: What, when thou blazest on the lesser altars, what to the #mighty Wind who comes to bless us, True, circumambient? what to $Earth, O @Agni, what wilt thou say to #man-destroying Rudra?\n\np: How to great @Pusan who promotes our welfare.to honoured Rudra what, who gives oblations? What sin of ours to the far-striding @Visnu, what, @Agni, wilt thou tell the Lofty Arrow.\n\np: What wilt thou tell the truthful band of #Maruts, how answer the great #Sun when thou art questioned? Before the Free, before the Swift, defend us: fulfil $Heaven's #work, all-knowing #Jatavedas.\n\np: I crave the #cow's true #gift arranged by #Order: though raw, she hath the sweet ripe #juice, O @Agni. Though she is black of hue with #milk she teemeth, nutritious, brightly shining, all-sustaining.\n\np: @Agni the Bull, the manly, hath been sprinkled with oil upon his back, by #Law eternal. He who gives vital power goes on unswerving. Prsni the Bull hath milked the pure wiiite udder.\n\np: By Law the #Angirases cleft the rock asunder, and sang their hymns together with the #cattle. Bringing great #bliss the #men encompassed #Morning: #light was apparent at the birth of @Agni.\n\np: By Law the #Immortal Devis the #Waters, with #meath-rich waves, O @Agni, and uninjuredlike a #strong courser lauded in his running, sped to #flow onward swiftly and forever.\n\np: Go never to the feast of one who harms us, the treacherous neighbour or unworthy kinsman. Punish us not for a false #brother's trespass. Let us not feel the #might of #friend or foeman.\n\np: O @Agni, keep us safe with thy protection, loving us, honoured @Deva. and ever guarding. Beat thou away, destroy severe affliction subdue e’en the demon when he waxes #mighty.\n\np: Through these our #songs of #praise be gracious, @Agni, moved by our meditations, O #Hero, touch our #offerings. Accept, O @Angiras, these our devotions, and let the #praise which #Devas desire address thee.\n\np: To thee who knowest, @Agni, thou Disposer, all these #wise secret speeches have I uttered, Sung to thee, #Sage, the charming words of wisdom, to thee, O #Singer, with. my thoughts and Praises.","people":["@Agni","@Angiras","@Visnu","@Mitra","@Varuna","@Visnu","@Pusan","@Bhaga","@Deva","@Aryaman"],"places":["$Earth","$Heaven"],"things":["#Worship","#Meath","#Milk","#Work","#Lord","#Waters","#Law Eternal","#Singer","#Light","#Sun","#Men","#Flow","#Might","#Juice","#Song","#Wise","#Strong","#Mighty","#Praise","#Hymn","#Gift","#Worship","#Offerings","#Bliss","#Songs","#Friend","#Hero","#Sage","#Cow","#Order","#Morning","#Cattle"],"groups":["#Devas","#Maruts","#Jatavedas","#Brother","#Husband","#Immortal","#Angirases","#Man"],"concepts":["Good","Birth","Friendship","Immortal","Wisdom","Offerings","Truthful","Circumambient","Swift"],"hash":"md5-lnSlTIyDJMNqASSW2pIoQA==","created":"Wednesday, November 22, 2023 - 6:01:41 AM"},{"id":"2ad90a24-7992-4316-a0c0-ec61bbfe98c2","key":"04004","book":"04","title":"HYMN IV. Agni.","link":"https://indra.ai/rigveda/hymns/04004.html","text":"p: PUT forth like a wide-spreading net thy vigour; go like a #mighty #King with his @Attendants. Thou, following thy swift net, shootest arrows: transfix the fiends with darts that burn most fiercely.\n\np: Forth go in rapid flight thy whirling weapons: follow them closely, glowing in thy fury. Spread with thy tongue the winged flames, O @Agni; unfettered, cast thy firebrands all around thee.\n\np: Send thy spies forward, fleetest in thy motion; be, ne’er deceived, the guardian of this #people From him who, near or far, is bent on evil, and let no trouble sent from thee o’ercome us.\n\np: Rise up, O @Agni, spread thee out before us: burn down our foes, thou who hast sharpened arrows. Him, blazing @Agni! who hath worked us mischief, consume thou utterly like dried-up stubble.\n\np: Rise, @Agni, drive off those who fight against us: make manifest thine own celestial vigour. Slacken the #strong bows of the demon-driven: destroy our foemen whether kin or stranger.\n\np: Most Youthful @Deva, he knoweth well thy favour who gave an impulse to this high devotion. All fair days and magnificence of #riches hast thou beamed forth upon the good #man's portals.\n\np: Blest, @Agni, be the #man, the liberal giver, who with his lauds and regular oblation Is fain to please thee for his #life and dwelling. May all his days be bright: be this his longing.\n\np: I #praise thy gracious favour: sing in answer. May this my #song sing like a loved one with thee. Lords of good #steeds and #car. May we adorn thee, and day by day vouchsafe thou us dominion.\n\np: Here of free choice let each one serve thee richly, resplendent day by day at eve and #morning. May we honour thee, content and joyous, passing beyond the glories of the #people.\n\np: Whoso with good #steeds and fine #gold, O @Agni, comes nigh thee on a #car laden with #treasure., His #Friend art thou, yea, thou art his Protector whose #joy it is to entertain thee duly.\n\np: Through words and kinship I destroy the #mighty: this power I have from @Gotama my #father. Mark thou this speech of ours, O thou Most Youthful, #Friend of the House, exceeding #wise, invoker.\n\np: Knowing no slumber, speedy and propitious, alert and ever friendly, most unwearied, may thy protecting #powers, unerring @Agni, taking their places here, combined, preserve us.\n\np: Thy guardian rays, O @Agni, when they saw him, preserved blind Mamateya from affliction. #Lord of all #riches, he preserved the pious: the fees who fain would harm them did no mischief\n\np: Aided by thee with the, may we be wealthy. May we gain strength with thee to guide us onward. Fulfil the words of both, O Ever Truthful: straightway do this, thou @Deva whom power emboldens.\n\np: O @Agni, with this fuel will we serve thee; accept the laud we sing to thee with favour Destroy the cursing @Raksasas: preserve us, O rich in #friends, from guile and scorn and slander.","people":["@Agni","@Deva","@Raksasas","@Attendants","@Gotama"],"places":[],"things":["#Steeds","#Lord","#Treasure","#Song","#Joy","#Gold","#Wise","#Strong","#Mighty","#Car","#Praise","#People","#Powers","#Friends","#Friend","#King","#Riches","#Morning","#Life"],"groups":["#Father","#Man"],"concepts":["Celestial","Good","Evil","Life","Strength","Giver","Truthful","Swift"],"hash":"md5-7lcdeIVntMCdlze1xBnbHQ==","created":"Wednesday, November 22, 2023 - 6:01:41 AM"},{"id":"27985650-d9da-4767-a426-3a46cc8be0e0","key":"04005","book":"04","title":"HYMN V. Agni.","link":"https://indra.ai/rigveda/hymns/04005.html","text":"p: How shall we give with one accord oblation to @Agni, to @Vaisvanara the Bounteous? Great #light, with full high growth hath he uplifted, and, as a pillar bears the roof, sustains it.\n\np: Reproach not him who, @Deva.and self-reliant, vouchsafed this bounty unto me a mortal. Deathless, discerner, #wise, to me the simple, @Vaisvanara most manly, youthful @Agni.\n\np: Sharp-pointed, powerful, #strong, of boundless vigour, @Agni who knows the lofty #hymn, kept secret As the lost #MilchCow's track, the doubly #Mighty.he hath declared to me this hidden knowledge.\n\np: May he with sharpened teeth, the Bounteous Giver, @Agni, consume with flame most fiercely glowing. Those who regard not @Varuna's commandments and the dear stedfast laws of sapient @Mitra.\n\np: Like youthful women without brothers, straying, like #dames who hate their lords, of evil conduct, they who are full of sin, untrue, unfaithful, they have engendered this abysmal station.\n\np: To me, weak, innocent luminous @Agni, hast boldly given as ’twere a heavy burthen, This Prstha #hymn, profound and #strong and #mighty, of seven #elements, and with offered dainties.\n\np: May our #song that purifies, through wisdom reach in a moment him the Universal, Established on the height, on $Earth's best station, above the beauteous grassy skin of Prsni.\n\np: Of this my speech what shall I utter further? They indicate the #milk stored up in secret When they have thrown as ’twere the cows' stalls open. The #Bird protects earths’ best and well-loved station.\n\np: This is the Great Ones’ #mighty apparition which from of old the radiant #Cow hath followed. This, shining brightly in the place of #Order, swift, hasting on in secret, she discovered.\n\np: He then who shone together with his #Parents remembered Prsni's fair and secret #treasure., Which, in the #Mother #Cow's most lofty station, the Bull's tongue, of the flame bent forward, tasted.\n\np: With #reverence I declare the Law, O @Agni; what is, comes by thine #order, #Jatavedas. Of this, whate’er it be, thou art the Sovran, yea, all the #wealth that is in $Earth or $Heaven.\n\np: What is our #wealth therefrom, and what our #treasure.? Tell us O #Jatavedas, for thou knowest, what is our best course in this secret passage: we, unreproached, have reached a place far distant.\n\np: What is the limit, what the rules, the guerdon? Like fleet-foot coursers speed we to the contest. When will the Devis, the #Immortal's #Spouses, the #Dawns, spread over us the @SunDeva's #splendour?\n\np: Unsatisfied, with speech devoid of vigour, scanty and frivolous and inconclusive, Wherefore do they address thee here, O @Agni? Let these who have no weapons suffer sorrow.\n\np: The majesty of him the Good, the #Mighty, aflame, hath shone for #glory in the dwelling. He, clothed in #light, hath shone most fair to look on, wealthy in boons, as a #home shines with #riches.","people":["@Agni","@Mitra","@Varuna","@Deva","@Vaisvanara","@SunDeva"],"places":["$Earth","$Heaven"],"things":["#Milk","#Reverence","#Glory","#Light","#Treasure","#Wealth","#Song","#Elements","#Home","#Wise","#Strong","#Mighty","#Hymn","#Splendour","#Bird","#Cow","#Parents","#Riches","#Order","#MilchCow"],"groups":["#Jatavedas","#Dawns","#Dames","#Mother","#Immortal","#Spouses"],"concepts":["Good","Evil","Immortal","Wisdom","Giver","Powerful","Swift"],"hash":"md5-06duQ/f6Ql6AtcDQiMACnw==","created":"Wednesday, November 22, 2023 - 6:01:41 AM"},{"id":"74ece817-ef2d-432d-af65-7686fabdcdfe","key":"04006","book":"04","title":"HYMN VI. Agni.","link":"https://indra.ai/rigveda/hymns/04006.html","text":"p: PRIEST of our rite, stand up erect, O @Agni, in the #Devas’ service best of offerers, for over evei y thought thou art the Ruler: thou furtherest e’en the wisdom of the pious.\n\np: He was set down mid #men as Monk unerring, @Agni, #wise, welcome in our holy synods. Like @Indra, @Indra, @Varuna, and @Mitra, #Soma, @Maghavan, @Savitar, @Visnu he hath lifted up his #splendour, and like a builder raised his smoke to $Heaven.\n\np: The glowing ladle, filled with oil, is lifted; choosing #Devas’ service to the right he circles. Eager he rises like the new-wrought pillar which, firmly set and fixed, anoints the victims.\n\np: When sacred #grass is strewn and @Agni kindled, the Adhvaryu rises to, his task rejoicing. @Agni the Monk, like one who tends the #cattle, goes three times round, as from of old he wills it.\n\np: @Agni himself, the Monk, with measured motion, goes round, with sweet speech, cheerful, true to #Order. His fulgent flames run forth like vigorous #horses; all creatures are affrighted when he blazes.\n\np: Beautiful and auspicious is thine aspect, O lovely @Agni, terrible when spreading. Thy splendours are not covered by the darkness: detraction leaves no stain upon thy body.\n\np: Naught hindered his production, Bounteous Giver: his #Mother and his Sire were free to send him. Then as #Friend benevolent, refulgent, @Agni shone forth in #human habitations.\n\np: He, @Agni, whom the twice-five sisters, dwelling together, in the homes of #men engendered, Bright like a spear's tooth, wakened in the #morning, with powerful mouth and like an axe well-sharpened.\n\np: These thy Bay Coursers, @Agni, dropping fatness, ruddy vigorous, speeding straightly forward, and red #steeds, wonderful, of #mighty muscle, are to this service of the #Devas invited:\n\np: These brightly-shining games of thine, O @Agni, that move forever restless, all-subduinglike falcons hasting eagerly to the quarry, roar loudly like the army of the #Maruts.\n\np: To thee, O flaming @Deva, hath prayer been offered. Let the #Sage laud thee: give to him who worships. #Men have established @Agni as Invoker, fain to adore the #glory of the living.","people":["@Indra","@Agni","@Visnu","@Mitra","@Varuna","@Maghavan","@Savitar","@Visnu","@Deva"],"places":["$Heaven"],"things":["#Steeds","#Soma","#Glory","#Men","#Wise","#Mighty","#Grass","#Splendour","#Friend","#Sage","#Horses","#Order","#Morning","#Cattle"],"groups":["#Devas","#Maruts","#Human","#Mother"],"concepts":["Beautiful","Holy","Sacred","Wisdom","Giver","Auspicious","Powerful"],"hash":"md5-XsxEOE5ZMe7f8Wg5f0MWJg==","created":"Wednesday, November 22, 2023 - 6:01:41 AM"},{"id":"e1da5aa7-93c3-4021-b7a1-42c7bfff39b3","key":"04007","book":"04","title":"HYMN VII. Agni.","link":"https://indra.ai/rigveda/hymns/04007.html","text":"p: HERE by ordainers was this @Deva appointed first Invoker, best at #worship, to be praised at rites: Whom Apnavana, and the #Bhrgus caused to #shine bright-coloured in the wood, spreading from #home to #home.\n\np: When shall thy #glory as a @Deva, @Agni, be suddenly shown forth. For mortal #men have held thee fast, #adorable in all their homes,\n\np: Seeing thee faithful to the Law, most sapient, like the starry $Heaven, Illumining with cheerful ray each solemn rite in every house.\n\np: @Vivasvan's envoy living #men have taken as their ensign, swift, the ruler over all #mankind, moving like Bhrgu in each #home.\n\np: Him the intelligent have they placed duly as Invoking Monk, Welcome, with sanctifying flame, best #worshipper, with sevenfold #might;\n\np: In his Eternal Mothers, in the wood, concealed and unapproached, Kept secret though his flames are bright seeking on all sides, quickly found.\n\np: That as #food spreads forth in this earthly udder, @Deva. May rejoice them in the #home of #Order, Great @Agni, served with #reverence and oblation, flies ever to  'the #offering, the Faithful.\n\np: #Bird of each rite, skilled in an envoy's duties, knowing both worlds and that which lies between them, Thou goest from of old a willing Herald, knowing full well $Heaven's innermost recesses.\n\np: Bright @Deva, thy path is black: #light is before thee: thy moving #splendour is the #chief of wonders. When she, yet unimpregnate, hath conceived thee, even when newly #born thou art an envoy.\n\np: Yet newly #born, his vigour is apparent when the wind blows upon his fiery #splendour, His sharpened tongue he layeth on the brushwood, and with his teeth e’en solid #food consumeth.\n\np: When he hath borne off #food with swift flame swiftly, #strong @Agni makes himself a speedy envoy, Follows the rustling of the wind, consuming, and courser-like, speeds, drives the swift #horse onward.","people":["@Agni","@Vivasvan","@Deva"],"places":["$Heaven"],"things":["#Worship","#Mankind","#Mankind","#Born","#Reverence","#Glory","#Offering","#Shine","#Light","#Food","#Men","#Might","#Home","#Strong","#Chief","#Worshipper","#Adorable","#Splendour","#Worship","#Offering","#Bird","#Horse","#Order"],"groups":["#Bhrgus"],"concepts":["Offering","Swift"],"hash":"md5-VZqLqidceUrzh5n4WiZYBQ==","created":"Wednesday, November 22, 2023 - 6:01:41 AM"},{"id":"8221af08-7259-4e94-bbce-fe580f4c3742","key":"04008","book":"04","title":"HYMN VIII. Agni.","link":"https://indra.ai/rigveda/hymns/04008.html","text":"p: YOUR envoy who possesses all, #Immortal, bearer of your #gifts, best #worshipper, I woo with #song.\n\np: He, #Mighty, knows the #gift of #wealth, he knows the deep recess of $Heaven: He shall bring hitherward the #Devas.\n\np: He knows, a @Deva.himself, to guide #Devas to the righteous in his #home: He gives e’en #treasure.s that we love.\n\np: He is the Herald: well-informed, he doth his errand to and fro, knowing the deep recess of $Heaven.\n\np: May we be they who gratify @Agni with #offerings #gifts, who cherish and enkindle him.\n\np: Illustrious for #wealth are they, and #hero deeds, victorious, who have served @Agni reverently.\n\np: So unto us, day after day. May #riches craved by many come, and power and #might spring up for us.\n\np: That holy #Singer in his strength shoots forth his arrows swifter than The swift shafts of the tribes of #men.","people":["@Agni","@Deva"],"places":["$Heaven"],"things":["#Singer","#Treasure","#Wealth","#Men","#Might","#Song","#Home","#Mighty","#Worshipper","#Gift","#Offerings","#Hero","#Riches","#Gifts"],"groups":["#Devas","#Immortal"],"concepts":["Love","Immortal","Holy","Strength","Offerings","Swift"],"hash":"md5-YXdp9G+/SvkQdKa9TpfMLA==","created":"Wednesday, November 22, 2023 - 6:01:41 AM"},{"id":"4fa107f0-3443-43dc-b966-fa35656eae03","key":"04009","book":"04","title":"HYMN IX. Agni.","link":"https://indra.ai/rigveda/hymns/04009.html","text":"p: @Agni, show favour: great art thou who to this pious #man art come, to seat thee on the sacred #grass.\n\np: May he the #Immortal. Helper, bard to be deceived among #mankind, become the messenger of all.\n\np: Around the altar is he led, welcome #Chief Monk at solemn rites, or as the @Potar sits him down.\n\np: @Agni in fire at #offering, and in the house as #Lord thereof, and as a Brahman takes his seat.\n\np: Thou comest as the guide of folk who celebrate a #offering, and to oblations brought by #men.\n\np: Thou servest as his messenger whose #offering thou lovest well, to bear the mortal's #gifts to $Heaven.\n\np: Accept our solemn rite; be pleased, @Angiras, with  'our #offering: Give ear and listen to our #call.\n\np: May thine inviolable #car, wherewith thou guardest those who give, Come near to us from every side.","people":["@Agni","@Angiras","@Potar"],"places":["$Heaven"],"things":["#Mankind","#Lord","#Mankind","#Offering","#Men","#Grass","#Car","#Chief","#Offering","#call","#Gifts"],"groups":["#Immortal","#Man"],"concepts":["Immortal","Sacred","Offering","Pleased"],"hash":"md5-gbd5Dp3x+pVO6FZVnWIWuQ==","created":"Wednesday, November 22, 2023 - 6:01:41 AM"},{"id":"81c61c91-5f4b-4f42-aafe-da12f0966af8","key":"04010","book":"04","title":"HYMN X. Agni.","link":"https://indra.ai/rigveda/hymns/04010.html","text":"p: This day with praises, @Agni, we bring thee that which thou lovest. Right judgment, like a #horse, with our devotions.\n\np: For thou hast ever been the #Car-driver, @Agni, of noble Strength, lofty #offering, and rightful judgment.\n\np: Through these our praises come thou to meet us, bright as the sunlight, O @Agni, well disposed, with all thine aspects.\n\np: No. May we serve thee singing these lauds this day to thee, @Agni. Loud as the #voice of $Heaven thy blasts are roaring.\n\np: Just at this time of the day and the night thy look is the sweetest: It shineth near us even as #gold for #glory.\n\np: Spotless thy body, brilliant as #gold, like clarified butter: This gleams like #gold on thee, O Self. dependent.\n\np: All hate and mischief, yea, if committed, @Agni, thou turnest, Holy One, from the #man who rightly worships.\n\np: @Agni, with you #Devas, prosperous be our friendships and kinships. Be this our bond here by this place, thine altar.","people":["@Agni"],"places":["$Heaven"],"things":["#Glory","#Offering","#Gold","#Car","#Voice","#Offering","#Horse"],"groups":["#Devas","#Man"],"concepts":["Holy","Strength","Offering","Noble"],"hash":"md5-EN3AahgvWM9nvk2smew0SQ==","created":"Wednesday, November 22, 2023 - 6:01:41 AM"},{"id":"d25f1d14-3e5d-4f00-86dd-e3312c94cbcd","key":"04011","book":"04","title":"HYMN XI. Agni.","link":"https://indra.ai/rigveda/hymns/04011.html","text":"p: THY blessed majesty, victorious @Agni, shines brightly in the neighbourhood of @Surya. Splendid to see, it shows even at nighttime, and #food is fair to look on in thy #beauty.\n\np: @Agni, disclose his thought for him who singeth, the well, #Strong @Deva. while thou art praised with fervour. Vouchsafe to us that powerful #hymn, O #Mighty, which, Radiant One! with all the #Devas thou lovest.\n\np: From thee, O @Agni, springs poetic wisdom, from thee come thoughts and hymns of #praise that prosper; From thee flows #wealth, with #heroes to adorn it, to the true-hearted #man who gives oblation.\n\np: From thee the #hero springs who wins the booty, bringer of #help, #mighty, of real courage. From thee comes #wealth, sent by the #Devas, #bliss-giving; @Agni, from thee the fleet impetuous charger.\n\np: #Immortal @Agni, thee whose #voice is pleasant, as first in rank, as @Deva, religious mortals Invite with hymns; thee who removest hatred, #Friend of the #Home, the household's #Lord, unerring.\n\np: Far from us thou removest want and sorrow, far from us all ill-will when thou protectest. #Son of Strength, @Agni, blest is he at evening, whom thou as @Deva.attendest for his welfare.","people":["@Agni","@Deva","@Surya"],"places":[],"things":["#Lord","#Wealth","#Food","#Beauty","#Help","#Home","#Strong","#Mighty","#Praise","#Voice","#Hymn","#Heroes","#Bliss","#Friend","#Hero"],"groups":["#Devas","#Son","#Immortal","#Man"],"concepts":["Immortal","Strength","Wisdom","Powerful"],"hash":"md5-+53hwVRdK0SO63fvzC+7XA==","created":"Wednesday, November 22, 2023 - 6:01:41 AM"},{"id":"69e6ecd8-a692-49b0-93b6-d788cd3ae063","key":"04012","book":"04","title":"HYMN XII. Agni.","link":"https://indra.ai/rigveda/hymns/04012.html","text":"p: WHOSO enkindles thee, with lifted ladle, and thrice this day #offers thee #food, O @Agni, may he excel, triumphant through thy splendours, #wise through thy mental power, O #Jatavedas.\n\np: Whoso with toil and trouble brings thee fuel, serving the majesty of #mighty @Agni. He, kindling thee at evening and at #morning, prospers, and comes to #wealth, and subdues his foemen.\n\np: @Agni is #Master of sublime dominion, @Agni is #Lord of strength and lofty #riches. Straightway the self-reliant @Deva, most Youthful, gives #treasure.s to the mortal who adores him.\n\np: Most Youthful @Deva, whatever sin, through folly, we here, as #human beings, have committed, in sight of @Aditi make thou us sinless remit, entirely, @Agni, our offences.\n\np: Even in the presence of great sin, O @Agni, free us from prison of the #Devas or mortals. Neve. May we who are thy #friends be injured: grant health and strength unto our seed and #offspring.\n\np: Even as ye here, #Devas #Excellent and Holy, have loosed the #cow that by the foot was tethered, So also set us free from this affliction long let our #life, O @Agni, be extended.","people":["@Agni","@Deva","@Aditi"],"places":[],"things":["#Master","#Lord","#Treasure","#Wealth","#Food","#Wise","#Offspring","#Mighty","#Offers","#Excellent","#Friends","#Cow","#Riches","#Morning","#Life"],"groups":["#Devas","#Jatavedas","#Human"],"concepts":["Life","Holy","Strength"],"hash":"md5-R26+hKWoPAXFTEi2QtcnvA==","created":"Wednesday, November 22, 2023 - 6:01:41 AM"},{"id":"628ce713-45b9-45ed-a3c4-579c439c1e07","key":"04013","book":"04","title":"HYMN XIII. Agni.","link":"https://indra.ai/rigveda/hymns/04013.html","text":"p: @Agni hath looked, benevolently-minded, on the #wealth-giving spring of radiant Mornings. Come, @Asvins, to the dwelling of the pious: @Surya the @Indu is rising with his #splendour.\n\np: @Indra, @Indra, @Varuna, and @Mitra, #Soma, @Maghavan, @Savitar, @Visnu, @Deva, hath spread on high his lustre, waving his flag like a #spoil-seeking #hero. Their stablished way go @Varuna and @Mitra, what time they make the #Sun #ascend the $Heaven.\n\np: Him whom they made to drive away the darkness, Lords of sure mansions, constant to their objecthim who beholds the universe, the @SunDeva, seven #strong and youthful Coursers carry onward.\n\np: Spreading thy web with mightiest #Steeds thou comest, rending apart, thou @Deva, the black-hued mantle. The rays of @Surya tremulously shining sink, like a hide, the darkness in the #waters.\n\np: How is it that, unbound and not supported, he falleth not although directed downward? By what self power moves he? Who hath seen it? He guards the vault of $Heaven, a close-set pillar.","people":["@Indu","@Indra","@Agni","@Visnu","@Mitra","@Varuna","@Asvins","@Maghavan","@Savitar","@Visnu","@Deva","@Surya","@SunDeva"],"places":["$Heaven"],"things":["#Steeds","#Soma","#Waters","#Sun","#Wealth","#Strong","#Ascend","#Splendour","#Hero","#spoil"],"groups":[],"concepts":[],"hash":"md5-u09v3gAceAPssx6aLLdNig==","created":"Wednesday, November 22, 2023 - 6:01:41 AM"},{"id":"734e2146-f19c-4ecc-b817-35fededb0917","key":"04014","book":"04","title":"HYMN XIV. Agni.","link":"https://indra.ai/rigveda/hymns/04014.html","text":"p: THE @Deva.hath looked, even @Agni #Jatavedas, to meet the #Dawns refulgent in their glories. Come on your chariot, ye who travel widely, come to this #offering of ours, @Nasatyas.\n\np: Producing #light for all the world of creatures, @Deva.@Indra, @Indra, @Varuna, and @Mitra, #Soma, @Maghavan, @Savitar, @Visnu hath raised aloft his banner. Making his presence known by sunbeams, @Surya hath filled the $Firmament and $Earth and $Heaven.\n\np: Red @Dawn is come, riding with brightness onward, distinguished by her beams, gay-hued and #mighty. @Dawn on her nobly-harnessed #car, the Devi, awaking #men to happiness, approacheth.\n\np: May those most powerful #steeds and chariot bring you, O @Asvins, hither at the break of #morning. Here for your draught of #meath are #Soma juices: at this  'our #offering rejoice, ye #Mighty.\n\np: How is it that, unbound and unsupported, he falleth not although directed downward? By what self-power moves he? Who hath seen it? He guards the vault of $Heaven, a close-set pillar?","people":["@Indra","@Agni","@Visnu","@Mitra","@Varuna","@Asvins","@Nasatyas","@Maghavan","@Savitar","@Visnu","@Deva","@Surya","@Dawn"],"places":["$Earth","$Heaven","$Firmament"],"things":["#Meath","#Steeds","#Soma","#Offering","#Light","#Men","#Mighty","#Car","#Offering","#Morning"],"groups":["#Jatavedas","#Dawns"],"concepts":["Offering","Powerful"],"hash":"md5-6gG76wk8Q7Eta0hKDxh/NQ==","created":"Wednesday, November 22, 2023 - 6:01:41 AM"},{"id":"696c4e91-9339-4b42-afa7-5f35b0dac66c","key":"04015","book":"04","title":"HYMN XV. Agni.","link":"https://indra.ai/rigveda/hymns/04015.html","text":"p: @Agni the Herald, like a #horse, is led forth at our solemn rite, @Deva.among #Devas #adorable.\n\np: Three times unto our solemn rite comes @Agni like a charioteer, bearing the #offerings to the #Devas.\n\np: Round the oblations hath he paced, @Agni the #Wise, the #Lord of Strength, giving the offerer precious boons.\n\np: He who is kindled eastward for Srnjaya, Devavata's #son, Resplendent, tamer of the foe.\n\np: So #mighty be the @Agni whom the mortal #hero shall command, with sharpened teeth and bountiful.\n\np: Day after day they dress him, as they clean a #horse who wins the prize. Dress the red Scion of the $Sky.\n\np: When Sahadeva's princely #son with two #bay #horses thought of me, Summoned by him I drew not back.\n\np: And truly those two noble bays I straightway took when offered me, From Sahadeva's princely #son.\n\np: Long, O ye @Asvins. May he live, your care, ye #Devas, the princely #son. Of Sahadeva, Somaka.\n\np: Cause him the youthful prince, the #son of Sahadeva, to enjoy Long #life, O @Asvins, O ye #Devas.","people":["@Agni","@Asvins","@Deva"],"places":["$Sky"],"things":["#Lord","#Wise","#Mighty","#Adorable","#Bay Horses","#Offerings","#Hero","#Horses","#Horse","#Life"],"groups":["#Devas","#Son"],"concepts":["Life","Strength","Offerings","Noble"],"hash":"md5-tJUKNX0oxH8EIAJdVwEQ9w==","created":"Wednesday, November 22, 2023 - 6:01:41 AM"},{"id":"02c81e4d-79d8-4bd0-8a14-6ecc86db2dff","key":"04016","book":"04","title":"HYMN XVI. Indra.","link":"https://indra.ai/rigveda/hymns/04016.html","text":"p: IMPETUOUS, true, let @Indra, @Indra, @Varuna, and @Mitra, #Soma, @Maghavan, @Savitar, @Visnu come hither, and let his #Tawny Coursers speed to reach us. For him have we pressed #juice exceeding potent: here, praised with #song, let him effect his visit.\n\np: Unyoke, as at thy #journey's end, O #Hero, to gladden thee today at this libation. Like @Usana, the #Sage a laud shall utter, a #hymn to thee, the #Lord Divine, who markest.\n\np: When the Bull, quaffing, praises our libation, as a #sage paying holy rites in secret, Seven singers here from $Heaven hath he begotten, who e’en by day have wrought their works while singing.\n\np: When $Heaven's fair #light by hymns was made apparent (they made great #splendour #shine at break of #morning). He with his assist, best of #Heroes, scattered the blinding darkness so that #men saw clearly.\n\np: @Indra, Impetuous One, hath waxed immensely: he with his vastness hath filled $Earth and $Heaven. E’en beyond this his majesty extendeth who hath exceeded all the worlds in greatness.\n\np: @Sakra who knoweth well all #human actions hath with his eager #Friends let loose the #waters. They with their #songs cleft e’en the mountain open and willingly disclosed the stall of #cattle.\n\np: He smote away the floods' obstructer, @Vrtra; $Earth, conscious, lent her aid to speed thy thunder. Thou sentest forth the #waters of the $Ocean, as #Lord through power and #might, O daring #Hero.\n\np: When, Much-invoked! the #water's rock thou cleftest, @Sarama showed herself and went before thee. Hymned by #Angirases, bursting the #cow-stalls, much strength thou foundest for us as our #leader.\n\np: Come, @Indra, @Indra, @Varuna, and @Mitra, #Soma, @Maghavan, @Savitar, @Visnu, #Friend of #Man, to aid the #singer imploring thee in battle for the sunlight. Speed him with #help in his inspired invokings: down sink the sorcerer, the prayerless #Dasyu.\n\np: Come to our #home resolved to subdue the #Dasyu: @Kutsa longed eagerly to win thy friendship. Alike in #form ye both sate in his dwelling the faithful Lady was in doubt between you.\n\np: Thou comest, fain to assist him, with @Kutsa.a goad that #masters both the Wind-@Deva's #horses, that, holding the brown #steeds like #spoil for capture, the sag. May on the final day be present.\n\np: For @Kutsa, with thy thousand, thou at day-break didst hurl down greedy @Susna, foe of harvest. Quickly with @Kutsa's #friend destroy the #Dasyus, and roll the chariot-wheel of @Surya near us.\n\np: Thou to the #son of Vidathin, @Rjisvan, gavest up #mighty Mrgaya and Pipru. Thou smotest down the swarthy fifty thousand, and rentest forts as age consumes a garment.\n\np: What time thou settest near the #Sun thy body, thy #form, #Immortal One, is seen expanding: Thou a wild elephant with #might invested. like a dread lion as thou wieldest weapons.\n\np: Wishes for #wealth have gone to @Indra, longing for him in war for #light and at libation, Eager for #glory, labouring with praisesongs: he is like #home, like sweet and fair nutrition.\n\np: #Call we for you that @Indra, prompt to listen, him who hath done so much for #men's advantage. Who, #Lord of envied bounty, to a #singer like me brings quickly booty worth the capture.\n\np: When the sharp-pointed arrow, O thou #Hero, flieth mid any conflict of the #people, when, Faithful One, the dread encounter cometh, then be thou the Protector of our body.\n\np: Further the holy thoughts of Vamadeva be thou a guileless #Friend in fight for booty. We come to thee whose providence protects us: wide be thy sway forever for thy #singer.\n\np: O @Indra, with these #men who love thee truly, free givers, @Indra, @Indra, @Varuna, and @Mitra, #Soma, @Maghavan, @Savitar, @Visnu, in every battle, may we rejoice through many autumns, quelling our foes, as days subdue the nights with #splendour.\n\np: Now, as the #Bhrgus wrought a #car, for @Indra the #Strong, the #Mighty, we our #meditation have fashioned, that h. May, ne’er withdraw from us his friendship, but be our bodies' guard and #strong defender.\n\np: Now, @Indra! lauded, glorified with praises, let power swell. high like #rivers for the #singer. For thee a new #hymn, #Lord of Bays, is fashioned. May we, #car-borne, through #song be victors ever.","people":["@Indra","@Vrtra","@Visnu","@Mitra","@Varuna","@Sakra","@Maghavan","@Susna","@Susna","@Savitar","@Visnu","@Usana","@Kutsa","@Deva","@Surya","@Rjisvan","@Sarama"],"places":["$Ocean","$Earth","$Heaven"],"things":["#Leader","#Masters","#Journey","#Tawny Coursers","#Steeds","#Lord","#Rivers","#Meditation","#Soma","#Waters","#Water","#Glory","#Singer","#Shine","#Light","#Sun","#Wealth","#Men","#Rivers","#Might","#Juice","#Song","#Help","#Home","#Strong","#Mighty","#Car","#Hymn","#Heroes","#Form","#Splendour","#People","#Lord of Bays","#Friends","#Songs","#Friend","#Hero","#Sage","#Cow","#Horses","#call","#spoil","#Morning","#Cattle"],"groups":["#Dasyus","#Dasyu","#Bhrgus","#Human","#Son","#Immortal","#Angirases","#Man"],"concepts":["Divine","Friendship","Love","Immortal","Holy","Strength"],"hash":"md5-zqpmC3tVUeMpeHbkfuO95A==","created":"Wednesday, November 22, 2023 - 6:01:42 AM"},{"id":"10a73869-97ac-4dd9-a455-9dcc7a5224d8","key":"04017","book":"04","title":"HYMN XVII. Indra.","link":"https://indra.ai/rigveda/hymns/04017.html","text":"p: GREAT art thou, @Indra; yea, the $Earth, with gladness, and $Heaven confess to thee thine high dominion. Thou in thy vigour having slaughtered @Vrtra didst free the floods arrested by the Dragon.\n\np: $Heaven trembled at the birth of thine effulgence; $Earth trembled at the fear of thy displeasure. The stedfast #mountains shook in agitation . the #waters flowed, and desert spots were flooded.\n\np: Hurling his bolt with #might he cleft the mountain, while, putting forth his strength, he showed his vigour. He slaughtered @Vrtra with his bolt, exulting, and, their #lord slain, forth flowed the #waters swiftly.\n\np: Thy #Father #Dyaus esteemed himself a #hero: most noble was the #work of @Indra's Maker, His who begat the #strong bolt's #Lord who roareth, immovable like $Earth from her foundation.\n\np: He who alone o’erthrows the world of creatures, @Indra the peoples' #King, invoked of many- Verily all rejoice in him, extolling the boons which @Indra, @Indra, @Varuna, and @Mitra, #Soma, @Maghavan, @Savitar hath sent them.\n\np: All #Soma juices are his own forever, most gladdening draughts are ever his, the #Mighty, Thou ever wast the #Treasure-#Lord of #treasure.s: @Indra, thou lettest all folk share thy bounty.\n\np: Moreover, when thou first wast #born, O @Indra, thou struckest terror into all the #people. Thou, @Indra, @Indra, @Varuna, and @Mitra, #Soma, @Maghavan, @Savitar, @Visnu, rentest with thy bolt the Dragon who lay against the waterfloods of $Heaven.\n\np: The ever-subduing, bold and furious @Indra, the bright bolt's #Lord, infinite, #strong and #mighty, who slayeth @Vrtra and acquireth booty, giver of blessings, @Indra, @Indra, @Varuna, and @Mitra, #Soma, @Maghavan, @Savitar, @Visnu the bounteous:\n\np: Alone renowned as @Indra, @Indra, @Varuna, and @Mitra, #Soma, @Maghavan, @Savitar, @Visnu in battles, he frighteneth away assembled #armies. He bringeth us the booty that he winnet. May we, well-loved, continue in his friendship.\n\np: Renowned is he when conquering and when subduing: 'fis he who winneth #cattle in the combat. When @Indra hardeneth his indignation all that is fixed and all that moveth fear him.\n\np: @Indra hath won all kine, all #gold, all #horses.@Indra, @Indra, @Varuna, and @Mitra, #Soma, @Maghavan, @Savitar, @Visnu, he who breaketh forts in pieces; Most manly with these #men of his who #help him, dealing out #wealth and gathering the #treasure..\n\np: What is the care of @Indra for his #Mother, what cares he for the #Father who begat him? His care is that which speeds his #might in conflicts, like wind borne onward by the clouds that thunder.\n\np: @Indra, @Indra, @Varuna, and @Mitra, #Soma, @Maghavan, @Savitar, @Visnu makes the settled #man unsettled: he scatters dust that he hath swept together, Breaking in pieces like $Heaven armed with lightning: @Indra, @Indra, @Varuna, and @Mitra, #Soma, @Maghavan, @Savitar, @Visnu shall enrich the #man who lauds h;m.\n\np: He urged the chariot-wheel of @Surya forward: @Etasa, speeding on his way, he rested. Him the black undulating cloud bedeweth, in this $$Mid-#Air's depth, at the base of darkness,\n\np: As in the night the sacrificing priest.\n\np: Eager for booty, craving strength and #horses, we-singers stir @Indra, the #strong, for friendship, who gives the wives we seek, whose assist fails not, to hasten, like a pitcher to the fountain.\n\np: Be thou our guardian, show thyself our kinsman, watching and #blessing those who pour the #Soma; As #Friend, as Sire, most fatherly of #fathers giving the suppliant vital strength and freedom.\n\np: Be helping #Friend of those who seek thy friendship . give #life, when lauded, @Indra, to the #singer. For, @Indra, we the monks have paid thee #worship, exalting thee with these  'our #offerings.\n\np: Alone, when @Indra @Indra, @Indra, @Varuna, and @Mitra, #Soma, @Maghavan, @Savitar, @Visnu is lauded, he slayeth many ne’er-resisted #Vrtras. Him in whose keeping is the well-loved #singer never do #Devas or mortals stay or hinder.\n\np: E’en so let @Indra, @Indra, @Varuna, and @Mitra, #Soma, @Maghavan, @Savitar, @Visnu, the loud-voiced @Indra, give us true blessings, foeless, #men's upholder. #King of all creatures, give us #glory amply, exalted #glory due to him who lauds thee.\n\np: Now, @Indra! lauded, glorified with praises, let power swell high like #rivers for the #singer. For thee a new #hymn, #Lord of Bays! is fashioned. May we, #car-borne, through #song be victors ever.","people":["@Indra","@Vrtra","@Visnu","@Mitra","@Varuna","@Maghavan","@Savitar","@Visnu","@Etasa","@Surya"],"places":["$Earth","$Heaven","$Mid-Air","$Mid-Air"],"things":["#Worship","#Work","#Lord","#Born","#Mountains","#Rivers","#Soma","#Waters","#Glory","#Singer","#Air","#Treasure","#Wealth","#Men","#Rivers","#Might","#Song","#Gold","#Help","#Strong","#Mighty","#Car","#Blessing","#Armies","#Hymn","#People","#Worship","#Lord of Bays","#Blessing","#Offerings","#Friend","#Hero","#King","#Horses","#Cattle","#Life"],"groups":["#Devas","#Dyaus","#Fathers","#Father","#Mother","#Man","#Vrtras"],"concepts":["Birth","Life","Friendship","Blessings","Strength","Offerings","Giver","Noble"],"hash":"md5-O8iXmyZT1ftUCtCNe9bobw==","created":"Wednesday, November 22, 2023 - 6:01:42 AM"},{"id":"1198aa8c-59f0-427c-951c-81b76c4f3ae1","key":"04018","book":"04","title":"HYMN XVIII. Indra and Others.","link":"https://indra.ai/rigveda/hymns/04018.html","text":"p: THIS is the ancient and accepted pathway by which all #Devas have come into existence. Hereby could one be #born though waxen #mighty. Let him not, otherwise, destroy his #Mother.\n\np: Not this way go I forth: hard is the passage. Forth from the side obliquely will I issue. Much that is yet undone must I accomplish; one must I combat and the other question.\n\np: He bent his eye upon the dying #Mother: My word I now withdraw. That way I follow. In @Tvastar's dwelling India drank the #Soma, a hundredworth of #juice pressed from the mortar.\n\np: What strange act shall he do, he whom his #Mother bore for a thousand months and many autumns? No peer hath he among those #born already, nor among those who shall be #born hereafter.\n\np: Deeming him a reproach, his #mother hid him, @Indra, endowed with all heroic valour. Then up he sprang himself, assumed his vesture, and filled, as soon as #born, the $Earth and $Heaven.\n\np: With lively motion onward #flow these #waters, the #Holy Ones, shouting, as ’twere, together. Ask them to. tell thee what the floods are saying, what girdling rock the #waters burst asunder.\n\np: Are they addressing him with words of welcome? Will the floods take on them the shame of @Indra? With his great thunderbolt my #Son hath slaughtered @Vrtra, and set these #rivers free to wander.\n\np: I cast thee from me, mine.thy youthful #mother: thee, mine own #offspring, Kusava hath swallowed. To him, mine infant, were the #waters gracious. @Indra, my #Son, rose up in conquering vigour.\n\np: Thou art mine own, O @Indra, @Indra, @Varuna, and @Mitra, #Soma, @Maghavan, @Savitar, @Visnu, whom Vyamsa struck to the ground and smote thy jaws in pieces. But, smitten through, the mastery thou wonnest, and with thy bolt the Dasa's head thou crushedst.\n\np: The Heifer hath brought forth the #Strong, the #Mighty, the unconquerable Bull, the furious @Indra. The #Mother left her unlicked Calf to wander, seeking himself, the path that he would follow.\n\np: Then to her #mighty #Child the #Mother turned her, saying, My #son, these #Deities forsake thee. Then @Indra said, about to slaughter @Vrtra, O my #friend @Vrtra, stride full boldly forward.\n\np: Who was he then who made thy #Mother widow? Who sought to stay thee lying still or moving? What @Deva, when by the foot thy Sire thou tookest and slewest, was at hand to give thee comfort?\n\np: In deep distress I cooked a dog's intestines. Among the #Devas I found not one to comfort. My consort I beheld in degradation. The Falcon then brought me the pleasant #Soma.","people":["@Indra","@Vrtra","@Visnu","@Mitra","@Varuna","@Maghavan","@Tvastar","@Savitar","@Visnu","@Deva"],"places":["$Earth","$Heaven"],"things":["#Holy Ones","#Born","#Rivers","#Soma","#Waters","#Rivers","#Flow","#Juice","#Offspring","#Strong","#Mighty","#Friend"],"groups":["#Devas","#Deities","#Mother","#Son","#Child"],"concepts":["Heroic","Holy"],"hash":"md5-AJ2FbeV1uB8dnlmjUjx42g==","created":"Wednesday, November 22, 2023 - 6:01:42 AM"},{"id":"c51bffa9-e7ed-410d-bd56-8fa4cd89dccd","key":"04019","book":"04","title":"HYMN XIX. Indra.","link":"https://indra.ai/rigveda/hymns/04019.html","text":"p: THEE, verily, O Thunder-wielding @Indra, all the #Devas here, the Helpers swift to listen, and both the worlds elected, thee the #Mighty, High, waxen #strong, alone to slaughter @Vrtra.\n\np: The #Devas, as worn witheld, relaxed their efforts: thou, @Indra, #born of truth, wast Sovran Ruler. Thou slewest Ahi who besieged the #waters, and duggest out their all-supporting channels.\n\np: The insatiate one, extended, hard to waken, who slumbered in perpetual sleep, O @Indra. The Dragon stretched against the seven prone #rivers, where no joint was, thou rentest with thy thunder.\n\np: @Indra with #might shook $Earth and her foundation as the wind stirs the #water with its fury. Striving, with strength he burst the firm asunder, and tore away the summits of the #mountains.\n\np: They ran to thee as mothers to their #offspring: the clouds, like #chariots, hastened forth together. Thou didst refresh the #streams and force the billows: thou, @Indra, settest free obstructed #rivers.\n\np: Thou for the sake of @Vayya and @Turviti didst stay the great #stream, flowing, all-sustaining: Yea, at their prayer didst check the rushing #river and make the floods easy to cross, O @Indra.\n\np: He let the young Maids skilled in Law, unwedded, like fountains, bubbling, #flow forth streaming onward. He inundated thirsty plains and deserts, and milked the dry Cows of the #mighty #master.\n\np: Through many a morn and many a lovely autumn, having slain @Vrtra, he set free the #rivers. @Indra hath set at liberty to wander on $Earth the #streams encompassed pressed together.\n\np: #Lord of Bay #Steeds, thou broughtest from the ant-hill the unwedded damsel's #son whom ants were eating. The blind saw clearly, as he grasped the serpent, rose, brake the jar: his joints again united.\n\np: To the #wise #man, O #Sage and Sovran Ruler, the #man who knoweth all thine ancient exploits. Hath told these deeds of #might as thou hast wrought them, great acts, spontaneous, and to #man's advantage.\n\np: Now, @Indra! lauded, glorified with praises, let #powers swell high, like #rivers, for the #singer. For thee a new #hymn, #Lord of Bays! is fashioned. May we, #car-borne, through #song be victors ever.","people":["@Indra","@Vrtra","@Vayya","@Turviti"],"places":["$Earth"],"things":["#Master","#Steeds","#Lord","#Born","#Mountains","#Rivers","#Waters","#Water","#Chariots","#Singer","#Rivers","#River","#Streams","#Stream","#Flow","#Might","#Song","#Wise","#Offspring","#Strong","#Mighty","#Car","#Hymn","#Lord of Bays","#Powers","#Sage"],"groups":["#Devas","#Son","#Man"],"concepts":["Strength","Truth","Swift"],"hash":"md5-6jiOCX7VKLUn9YfjtW+b5A==","created":"Wednesday, November 22, 2023 - 6:01:42 AM"},{"id":"e1a06f63-5212-43c6-8e48-60974097a981","key":"04020","book":"04","title":"HYMN XX. Indra.","link":"https://indra.ai/rigveda/hymns/04020.html","text":"p: FROM near or far awa. May #mighty @Indra giver of assist, come for our protection #Lord of #men, armed with thunder, with the Strongest, subduing his foes in conflict, in the battles.\n\np: May @Indra come to us with #Tawny Coursers, inclined to us, to favour and enrich us. May @Indra, @Indra, @Varuna, and @Mitra, #Soma, @Maghavan, @Savitar, @Visnu, loud-voiced and wielding thunder, stand by us at this #offering, in combat.\n\np: Thou, honouring this  'our #offering, O @Indra, shalt give us strength and fill us full of courage. To win the booty, Thunder-armed! like hunter. May we with thee subdue in fight our foemen.\n\np: Loving us well, benevolent, close beside us, drink, @Deva.ike @Indra, of the well-pressed #Soma. Drink of the #meath we offer, and #delight thee with #food that cometh from the mountain ridges.\n\np: Him who is sung aloud by recent sages, like a ripe-fruited tree, a scythe-armed victor. I, like a bridegroom thinking of his consort, #call hither @Indra, him invoked of many;\n\np: Him who in native strength is like a mountain, the lofty @Indra #born or old for conquest, Terrific wielder of the ancient thunder. filled full with #splendour as a jar with #water.\n\np: Whom from of old there is not one to hinder, none to curtail the #riches of his bounty. Pouring forth freely, O thou #Strong and #Mighty, vouchsafe us #riches, @Deva.invoked of many!\n\np: Of #wealth and homes of #men thou art the ruler, and opener of the stable of the #cattle. Helper of #men, winner of #spoil in combats, thou leadest to an ample heap of #riches.\n\np: By what great #might is he renowned as strongest, wherewith the Lofty One stirs up wild battles? Best soother of the #worshipper's great sorrow, he gives possessions to the #man who lauds him.\n\np: Slay us not; bring, bestow onus the ample #gift which thou hast to give to him who #offers. At this new #gift, with this laud sung before thee, extolling thee, we, @Indra, will declare it.\n\np: Now, @Indra! lauded, glorified with praises, let power swell high, like #rivers, for the #singer. A new #hymn, #Lord of Bays! for thee is fashioned. May we, #car-#born, through #song be victors ever.","people":["@Indra","@Visnu","@Mitra","@Varuna","@Maghavan","@Savitar","@Visnu","@Deva"],"places":[],"things":["#Meath","#Tawny Coursers","#Lord","#Born","#Rivers","#Soma","#Water","#Singer","#Offering","#Wealth","#Food","#Men","#Rivers","#Might","#Song","#Strong","#Mighty","#Car","#Worshipper","#Delight","#Hymn","#Gift","#Splendour","#Offers","#Lord of Bays","#Offering","#call","#spoil","#Riches","#Cattle"],"groups":["#Man"],"concepts":["Strength","Offering","Giver","Winner"],"hash":"md5-vQzXvVy5HAwy3hUcTbLe3g==","created":"Wednesday, November 22, 2023 - 6:01:42 AM"},{"id":"85a20cf5-d768-4273-ac67-c1d0ca23e4e0","key":"04021","book":"04","title":"HYMN XXI. Indra.","link":"https://indra.ai/rigveda/hymns/04021.html","text":"p: MAY @Indra come to us for our protection; here be the #Hero, praised, our feast-companion. May he whose #powers are many, waxen #mighty, cherish, like #Dyaus, his own supreme dominion.\n\np: Here magnify his great heroic exploits, most #glorious One, enriching #men with bounties, whose will is like a Sovran in assembly, who rules the #people, Conqueror, all-surpassing.\n\np: Hither let @Indra come from $Earth or $Heaven, hither with speech from $Firmament or $Ocean; With #Maruts, from the realm of #light to aid us, or from a distance, from the seat of #Order.\n\np: That @Indra will we laud in our assemblies, him who is #Lord of great and lasting #riches, Victor with @Vayu where the herds are gathered, who leads with boldness on to higher fortune.\n\np: May the Monk, #Lord of many blessings, striving.who fixing #reverence on #reverence, giving Vent to his #voice, inciteth #men to #worship—with lauds bring @Indra hither to our dwellings.\n\np: When sitting pondering in deep devotion in Ausija's abode they ply the press-stone, may he whose wrath is fierce, the #mighty bearer, come as the house-#lord's priest within our chambers.\n\np: Surely the power of Bharvara the #mighty forever helpeth to support the #singer; That which in Ausija's abode lies hidden, to come forth for #delight and for devotion.\n\np: When he unbars the spaces of the #mountains, and quickens with his floods the #water-torrents. He finds in lair the buffalo and wild-ox when the #wise lead him on to vigorous exploit.\n\np: Auspicious are thy hands, thine arms well-fashioned which proffer bounty, @Indra, to thy praiser. What sloth is this? Why dost thou not rejoice thee? Why dost thou not #delight thyself with giving?\n\np: So @Indra is the truthful #Lord of #treasure.. Freedom he gave to #man by subduing @Vrtra. Much-lauded! #help us with thy power to #riches. May I be sharer of thy @Deva.ike favour.\n\np: Now, @Indra! lauded, glorified with praises, let power swell high, like #rivers, for the #singer. For thee a new #hymn, #Lord of Bays! is fashioned. May we, care-borne, through #song be victors ever.","people":["@Indra","@Vrtra","@Vayu","@Deva"],"places":["$Ocean","$Earth","$Heaven","$Firmament"],"things":["#Worship","#Lord","#Mountains","#Rivers","#Reverence","#Water","#Glorious","#Singer","#Light","#Treasure","#Men","#Rivers","#Song","#Help","#Wise","#Mighty","#Voice","#Delight","#Hymn","#People","#Worship","#Lord of Bays","#Powers","#Hero","#Riches","#Order"],"groups":["#Dyaus","#Maruts","#Man"],"concepts":["Heroic","Blessings","Auspicious","Truthful","Glorious"],"hash":"md5-LTNdfdI3adUOOt7N6JcX7g==","created":"Wednesday, November 22, 2023 - 6:01:42 AM"},{"id":"9eb0f0e9-ff25-4472-a10a-9266bd9103d6","key":"04022","book":"04","title":"HYMN XXII. Indra.","link":"https://indra.ai/rigveda/hymns/04022.html","text":"p: THAT #gift of ours which @Indra loves and welcomes, even that he makes for us, the Great and #Strong One. He who comes wielding in his #might the thunder, @Indra, @Indra, @Varuna, and @Mitra, #Soma, @Maghavan, @Savitar, @Visnu, gives prayer, #praise, and laud, and #Soma.\n\np: Bull, hurler of the four-edged #rain-producer with both his arms, #strong, #mighty, most heroic; Wearing as wool Parusni for adornment, whose joints for sake of friendship he hath covered.\n\np: @Deva who of all the #Devas was #born divinest, endowed with ample strength and #mighty #powers, and bearing in his arms the yearning thunder, with violent rush caused $Heaven and $Earth to tremble.\n\np: Before the High @Deva, at his birth, $Heaven trembled, $Earth, many floods and all the precipices. The #Strong One bringeth nigh the Bull's two #Parents: loud sing the winds, like #men, in #air's mid-region.\n\np: These are thy great deeds, @Indra, thine, the #Mighty, deeds to be told aloud at all #libations, that thou, O #Hero, bold and boldly daring, didst with thy bolt, by strength, destroy the Dragon.\n\np: True are all these thy deeds, O Most Heroic. The Milch-kine issued from the streaming udder. In fear of thee, O thou of manly #spirit, the #rivers swiftly set themselves in motion.\n\np: With #joy, O @Indra, #Lord of #Tawny Coursers, the Sisters then, these Devis, extolled thee, when thou didst give the prisoned ones their freedom to wander at their will in long succession.\n\np: Pressed is the gladdening stalk as ’twere a #river: so let the rite, the toiler's power, attract thee To us-ward, of the Bright One, as the courser strains his. exceedingly #strong leather bridle.\n\np: Ever by us perform thy most heroic, thine highest, best victorious deeds, O Victor. For us make #Vrtras easy to be conquered: destroy the weapon of our mortal foeman.\n\np: Graciously listen to our #meditation, O @Indra, and strength of varied sort bestow thou on us. Send to us all intelligence arid wisdom O @Indra, @Indra, @Varuna, and @Mitra, #Soma, @Maghavan, @Savitar, @Visnu, be he who gives us #cattle.\n\np: Now, @Indra! lauded, glorified with praises, let #wealth swell high like #rivers to the #singer. For thee a new #hymn, #Lord of Bays, is fashioned. May we, #car-borne, through #song be victors ever.","people":["@Indra","@Visnu","@Mitra","@Varuna","@Maghavan","@Savitar","@Visnu","@Deva"],"places":["$Earth","$Heaven"],"things":["#Tawny Coursers","#Lord","#Born","#Rivers","#Meditation","#Soma","#Singer","#Air","#Wealth","#Men","#Rivers","#River","#Might","#Rain","#Song","#Joy","#Strong","#Mighty","#Car","#Praise","#Hymn","#Gift","#Lord of Bays","#Powers","#Libations","#Hero","#Parents","#Cattle","#Spirit"],"groups":["#Devas","#Vrtras"],"concepts":["Birth","Friendship","Heroic","Strength","Wisdom","Libations"],"hash":"md5-rPQC3abo20HRtO8Bn4bvgw==","created":"Wednesday, November 22, 2023 - 6:01:42 AM"},{"id":"af0f985e-1834-41d9-88ce-e245c095075f","key":"04023","book":"04","title":"HYMN XXIII. Indra.","link":"https://indra.ai/rigveda/hymns/04023.html","text":"p: How, what priest's #offering hath he made #mighty, rejoicing in the #Soma and its fountain? Delighting in #juice, eagerly drinking, the Lofty One hath waxed for splendid #riches.\n\np: What #hero hath been made his feast-companion? Who hath been partner in his loving-kindness? What know we of his wondrous acts? How often comes he to aid and speed the pious toiler?\n\np: How heareth @Indra offered invocation? How, hearing, marketh he the invoker's wishes? What are his ancient acts of bounty? Wherefore #call they him One who filleth full the #singer?\n\np: How doth the #Sage who laboureth, ever longing, win for himself the #wealth which he possesseth? May he, the @Deva, mark well my truthful praises, having received the homage which he loveth.\n\np: How, and what bond of friendship with a mortal hath the @Deva.chosen as this morn is breaking? How, and what love hath he for those who love him, who have entwined in him their firm affection?\n\np: Is then thy friendship with thy #friends most #mighty? Thy #brotherhood with us.whe. May we tell it? The #streams of #milk move, as most wondrous sunlight, the #beauty of the Lovely One for #glory.\n\np: About to stay the @Indra-less destructive #spirit he sharpens his keen arms to strike her. Whereby the #Strong, although our debts’ exactor, drives in the distant mornings that we know not.\n\np: Eternal Law hath varied #food that strengthens; thought of eternal Law, removes transgressions. The #praise-#hymn of eternal Law, arousing, glowing, hath oped the deaf ears of the living.\n\np: Firm-seated are eternal Law's foundations in its fair #form are many splendid beauties. By holy Law long lasting #food they bring us; by holy Law have cows come to our #worship.\n\np: Fixing eternal Law he, too, upholds it swift moves the #might of Law and wins the booty. To Law belong the vast deep $Earth and $Heaven: Milch-kine supreme, to Law their #milk they render.\n\np: Now, @Indra! lauded.glorified with praises, let power swell high like #rivers to the #singer. For thee a new #hymn, #Lord of Bays, is fashioned. May we, #car-borne, through #song be victors ever.","people":["@Indra","@Deva"],"places":["$Earth","$Heaven"],"things":["#Worship","#Milk","#Lord","#Rivers","#Soma","#Glory","#Singer","#Offering","#Wealth","#Food","#Rivers","#Streams","#Might","#Juice","#Song","#Beauty","#Strong","#Mighty","#Car","#Praise","#Hymn","#Form","#Worship","#Lord of Bays","#Offering","#Friends","#Hero","#Sage","#call","#Riches","#Spirit"],"groups":["#Brotherhood"],"concepts":["Friendship","Love","Holy","Offering","Truthful","Swift","Eternal Law"],"hash":"md5-7KHWNOd+zeGW2r9EHlECSw==","created":"Wednesday, November 22, 2023 - 6:01:42 AM"},{"id":"9c7b0f83-bf06-40a2-b4f7-7e179e03a679","key":"04024","book":"04","title":"HYMN XXIV. Indra.","link":"https://indra.ai/rigveda/hymns/04024.html","text":"p: WHAT worthy #praise will bring before us @Indra, the #Son of Strength, that h. May grant us #riches; For he the #Hero, gives the #singer #treasure.s: he is the #Lord who sends us #gifts, ye #people.\n\np: To be invoked and hymned in fight with @Vrtra, that well-praised @Indra gives us real bounties. That @Indra, @Indra, @Varuna, and @Mitra, #Soma, @Maghavan, @Savitar, @Visnu brings comfort in the foray to the religious #man who pours #libations.\n\np: Him, verily, the #men invoke in combat; risking their lives they make him their protector, when #heroes, foe to foe, give up their bodies, fighting, each side, for children and their #offspring.\n\np: #Strong @Deva. the folk at need put forth their vigour, striving together in the whirl of battle. When #warrior bands encounter one another some in the grapple quit themselves like @Indra.\n\np: Hence many a one worships the #might of @Indra: hence let the brew succeed the meal-oblation. Hence let the #Soma banish those who pour not: even hence I #joy to pay the #Strong One #worship.\n\np: @Indra gives comfort to the #man who truly presses, for him who longs for it, the #Soma, Not disaffected, with devoted #spirit this #man he takes to be his #friend in battles.\n\np: He who this day for @Indra presses #Soma, prepares the brew and fries the grains of barley— Loving the hymns of that devoted servant, to hi. May @Indra give heroic vigour.\n\np: When the impetuous #chief hath sought the conflict, and the #lord looked upon the long-drawn battle, the @Matron calls to the #Strong @Deva whom pressers of #Soma have encouraged in the dwelling.\n\np: He bid a small price for a thing of value: I was content, returning, still unpurchased. He heightened not his insufficient offer. Simple and clever, both #milk out the udder.\n\np: Who for ten milch-kine purchaseth from me this @Indra who is mine? When he hath slain the #Vrtras let the buyer give him back to me.\n\np: Now, @Indra! lauded, glorified with praises, let #wealth swell high like #rivers for the #singer. For thee a new #hymn, #Lord of Bays, is fashioned. May we, #car-borne, through #song be victors ever.","people":["@Indra","@Vrtra","@Visnu","@Mitra","@Varuna","@Maghavan","@Savitar","@Visnu","@Deva","@Matron"],"places":[],"things":["#Worship","#Milk","#Lord","#Rivers","#Soma","#Singer","#Treasure","#Wealth","#Men","#Rivers","#Might","#Song","#Joy","#Offspring","#Strong","#Car","#Chief","#Praise","#Hymn","#Heroes","#People","#Worship","#Lord of Bays","#Libations","#Warrior","#Friend","#Hero","#Riches","#Spirit","#Gifts"],"groups":["#Son","#Man","#Vrtras"],"concepts":["Heroic","Strength","Libations"],"hash":"md5-MKKaGfL86YlYe3UJeG/LHg==","created":"Wednesday, November 22, 2023 - 6:01:42 AM"},{"id":"0f45445a-92c2-449e-aa73-5ef58b8faf18","key":"04025","book":"04","title":"HYMN XXV. Indra.","link":"https://indra.ai/rigveda/hymns/04025.html","text":"p: WHAT #friend of #man, @Deva.loving, hath delighted, yearning therefor, this day in @Indra's friendship? Who with enkindled flame and flowing #Soma laudeth him for his great protecting favour?\n\np: Who hath with prayer bowed to the #Soma-lover? What pious #man endues the beams of #morning? Who seeks bond, friendship, #brotherhood with @Indra? Who hath recourse unto the #Sage for assist?\n\np: Who claims to-day the #Deities' protection, asks @Aditi for #light, or the @Adityas? Of whose pressed stalk of #Soma drink the @Asvins, @Indra, and @Agni, well-inclined in #spirit?\n\np: To him shall @Agni @Bharata give shelter: long shall he look upon the #Sun up-rising, who sayeth, Let us press the #juice for @Indra, #man's #Friend, the #Hero manliest of #heroes.\n\np: Him neither few #men overcome, nor many to him shall @Aditi give spacious shelter. Dear is the pious, the devout, to @Indra dear is the zealous, dear the #Soma-bringer.\n\np: This #Hero curbs the #mighty for the zealous: the presser's brew @Indra possesses solely: No #brother, kin, or #friend to him who pours not, destroyer of the dumb who would resist him.\n\np: Not with the wealthy churl who pours no #Soma doth @Indra, #Soma-drinker, bind alliance. He draws away his #wealth and subdues him naked, own #Friend to him who #offers, for oblation.\n\np: Highest and lowest, #men who stand between diem, going, returning, dwelling in contentment, Those who show forth their strength when urged to battle-these are the #men who #call for aid on @Indra.","people":["@Indra","@Agni","@Asvins","@Adityas","@Adityas","@Bharata","@Deva","@Aditi"],"places":[],"things":["#Soma","#Light","#Sun","#Wealth","#Men","#Juice","#Mighty","#Heroes","#Offers","#Friend","#Hero","#Sage","#call","#Morning","#Spirit"],"groups":["#Deities","#Brother","#Brotherhood","#Man"],"concepts":["Friendship","Strength","Devout"],"hash":"md5-a7gjiq1yWAGJX+9NdAWghA==","created":"Wednesday, November 22, 2023 - 6:01:42 AM"},{"id":"5d8f02e5-72f1-4d00-9bb8-b4ee4b1dbd87","key":"04026","book":"04","title":"HYMN XXVI. Indra.","link":"https://indra.ai/rigveda/hymns/04026.html","text":"p: I WAS aforetime Manu, I was @Surya: I am the #sage Kaksivan, holy #singer. @Kutsa the #son of Arjuni I #master. I am the sapient @Usana behold me.\n\np: I have bestowed the $Earth upon the Arya, and #rain upon the #man who brings oblation. I guided forth the loudly-roaring #waters, and the #Devas moved according to my pleasure.\n\np: In the wild #joy of #Soma I demolished Sambara's forts, ninety-and-nine, together; And, utterly, the hundredth habitation, when helping Divodasa @Atithigva.\n\np: Before all birds be ranked this #Bird, O #Maruts; supreme of falcons be this fleet-winged Falcon, because, #strong- pinioned, with no #car to bear him, he brought to Manu the @Deva.oved oblation.\n\np: When the #Bird brought it, hence in rapid motion sent on the wide path fleet as thought he hurried. Swift he returned with sweetness of the #Soma, and hence the Falcon hath acquired his #glory.\n\np: Bearing the stalk, the Falcon speeding onward, #Bird bringing from afar the draught that gladdens, #Friend of the #Devas, brought, grasping fast, the #Soma which be bad taken from yon loftiest $Heaven.\n\np: The Falcon took and brought the #Soma, bearing thousand #libations with him, yea, ten thousand. The Bold One left Malignities behind him, #wise, in wild #joy of #Soma, left the foolish.","people":["@Usana","@Kutsa","@Deva","@Surya","@Atithigva"],"places":["$Earth","$Heaven"],"things":["#Master","#Soma","#Waters","#Glory","#Singer","#Rain","#Joy","#Wise","#Strong","#Car","#Libations","#Friend","#Bird","#Sage"],"groups":["#Devas","#Maruts","#Son","#Man"],"concepts":["Holy","Libations","Swift"],"hash":"md5-C5/N9BvocxYZrHXF3sBNPQ==","created":"Wednesday, November 22, 2023 - 6:01:42 AM"},{"id":"d32d4b40-56a5-4aa0-b3f3-9667a4189fe6","key":"04027","book":"04","title":"HYMN XXVII. The Falcon.","link":"https://indra.ai/rigveda/hymns/04027.html","text":"p: I, as I lay within the womb, considered all generations of these #Devas in #order. A hundred iron fortresses confined me but forth I flew with rapid speed a Falcon.\n\np: Not at his own free pleasure did he bear me: he conquered with his strength and manly courage. Straightway the Bold One left the fiends behind him and passed the winds as he grew yet more #mighty.\n\np: When with loud cry from $Heaven down sped the Falcon, thence hasting like the wind he bore the Bold One. Then, wildly raging in his mind, the archer Krsanu aimed and loosed the string to strike him.\n\np: The Falcon bore him from $Heaven's lofty summit as the swift #car of @Indra's #Friend bore Bhujyu. Then downward hither fell a flying feather of the #Bird hasting forward in his #journey.\n\np: And now let @Indra, @Indra, @Varuna, and @Mitra, #Soma, @Maghavan, @Savitar, @Visnu accept the beaker, white, filled with #milk, filled with the shining liquid; The best of sweet #meath which the monks have offered: that @Indra to his jo. May drink, the #Hero, that h. May take and drink it to his rapture.","people":["@Indra","@Visnu","@Mitra","@Varuna","@Maghavan","@Savitar","@Visnu"],"places":["$Heaven"],"things":["#Meath","#Milk","#Journey","#Soma","#Mighty","#Car","#Friend","#Hero","#Bird","#Order"],"groups":["#Devas"],"concepts":["Strength","Swift"],"hash":"md5-+58asAOh2qCzAeJ2M8mFAw==","created":"Wednesday, November 22, 2023 - 6:01:42 AM"},{"id":"3a5ca119-eb5e-4354-89a8-53ea81e33a78","key":"04028","book":"04","title":"HYMN XXVIII. Indra, indra, Varuna, and Mitra, Soma, Maghavan, Savitar, Visnu.","link":"https://indra.ai/rigveda/hymns/04028.html","text":"p: ALLIED with thee, in this thy friendship, #Soma, @Indra for #man made #waters #flow together, Slew Ahi, and sent forth the Seven #Rivers, and opened as it were obstructed fountains.\n\np: @Indu, with thee for his confederate, @Indra swiftly with #might pressed down the wheel of @Surya. What rolled, all #life's support, on $Heaven's high summit was separated from the great oppressor.\n\np: @Indra smote down, @Agni consumed, O @Indu, the #Dasyus ere the noontide in the conflict. Of those who gladly sought a hard-won dwelling he cast down many a thousand with his arrow.\n\np: Lower than all besides hast thou, O @Indra, cast down the #Dasyus, abject tribes of Dasas. Ye drave away, ye put to #death the foemen, and took great vengeance with your murdering weapons.\n\np: So, of a truth, @Indra and #Soma. #Heroes, ye burst the stable of the kine and #horses, the stable which the bar or stone obstructed; and piercing through set free the habitations.","people":["@Indu","@Indra","@Agni","@Surya"],"places":["$Heaven"],"things":["#Rivers","#Soma","#Waters","#Rivers","#Flow","#Might","#Heroes","#Horses","#Life","#Death"],"groups":["#Dasyus","#Man"],"concepts":["Death","Life","Friendship","Truth"],"hash":"md5-eg2+93tvmlcFkhUN86PMUA==","created":"Wednesday, November 22, 2023 - 6:01:42 AM"},{"id":"110a110b-2136-48f1-a05c-ede17696a95c","key":"04029","book":"04","title":"HYMN XXIX. Indra.","link":"https://indra.ai/rigveda/hymns/04029.html","text":"p: COME, lauded, unto us with #powers and assists, O @Indra, with thy Tawny #Steeds; exulting, past even the foeman's manifold #libations, glorified with our hymns, true #Wealth-bestower.\n\np: #Man's #Friend, to this  'our #offering he cometh marking how he is called by #Soma-pressers. Fearless, and conscious that his #Steeds are noble, he joyeth with the #Soma-pouring #heroes.\n\np: Make his #cars hear, that h. May show his vigour an. May be joyful in the way he loveth. May #mighty @Indra pouring forth in bounty bestow on us good roads and perfect safety;\n\np: He who with assist comes to his implorer, the #singer here who with his #song invites him; He who himself sets to the pole swift Coursers, he who hath hundreds, thousands, Thunder-wielder.\n\np: O @Indra @Indra, @Indra, @Varuna, and @Mitra, #Soma, @Maghavan, @Savitar, @Visnu, by thee protecte. May we be thine, princes and monks and singers, Sharing the #riches sent from lofty $Heaven which yields much #food, and all desire its bounty.","people":["@Indra","@Visnu","@Mitra","@Varuna","@Maghavan","@Savitar","@Visnu"],"places":["$Heaven"],"things":["#Steeds","#Soma","#Singer","#Offering","#Wealth","#Food","#Song","#Mighty","#Heroes","#Powers","#Offering","#Libations","#Friend","#Riches","#Cars"],"groups":["#Man"],"concepts":["Good","Cars","Offering","Libations","Swift","Noble"],"hash":"md5-MXJlo3AkPoyLYBPoStMKlw==","created":"Wednesday, November 22, 2023 - 6:01:42 AM"},{"id":"43a59ef3-a41a-4251-9f34-61b402353f07","key":"04030","book":"04","title":"HYMN XXX. Indra.","link":"https://indra.ai/rigveda/hymns/04030.html","text":"p: O @Indra, @Vrtra conquerer, none is better, mightier than thou: Verily there is none like thee.\n\np: Like chariot-wheels these #people all together follow after thee: Thou ever art renowned as Great.\n\np: Not even all the gathered #Devas conquered thee, @Indra, in the war, when thou didst lengthen days by night.\n\np: When for the sake of those oppressed, and @Kutsa as he battled, Thou stolest away the #Sun's #car-wheel.\n\np: When, fighting singly, @Indra. thou o’ercamest all the furious #Devas, thou slewest those who strove with thee.\n\np: When also for a mortal #man, @Indra, thou speddest forth the #Sun, and holpest @Etasa with #might.\n\np: What? @Vrtra conquerer, art not thou, @Indra, @Indra, @Varuna, and @Mitra, #Soma, @Maghavan, @Savitar, @Visnu, fiercest in thy wrath? So hast thou quelled the demon too.\n\np: And this heroic deed of #might thou, @Indra, also hast achieved, that thou didst smite to #death the Dame. $Heaven's Daughter, meditating ill.\n\np: Thou, @Indra, #Mighty One, didst crush @Usas, though Daughter of the $Sky. When lifting up herself in pride.\n\np: Then from her chariot @Usas fled, affrighted, from her ruined #car. When the #strong @Deva.had shattered it.\n\np: So there this #car of @Usas lay, broken to pieces, in Vipas, and she herself fled far away.\n\np: Thou, @Indra, didst. with magic power resist the overflowing #stream Who spread her #waters o’er the land.\n\np: Valiantly didst thou seize and take the store which @Susna had amassed, when thou didst crush his fortresses.\n\np: Thou, @Indra, also smotest down Kulitara's #son Sambara, the Dasa, from the lofty hill.\n\np: Of Dasa Varcin's thou didst subdue the hundred thousand and the five, Crushed like the fellies, of a #car.\n\np: So @Indra, #Lord of #Heroes, #powers, caused the unwedded damsel's #son, the castaway, to share the lauds.\n\np: So sapient @Indra, #Lord of #Might, brought @Turvasa and @Yadu, those Who feared the flood, in safety o’er.\n\np: Arna and Citraratha, both Aryas @Indra, slewest swift, On yonder side of Sarayu,\n\np: Thou, @Vrtra conquerer, didst conduct those two forlorn, the blind, the lame. Non. May attain this #bliss of thine.\n\np: For Divodasa, him who brought oblations, @Indra overthrew A hundred fortresses of stone.\n\np: The thirty thousand Dasas he with magic power and weapons sent To slumber, for Dabhiti's sake.\n\np: As such, O @Vrtra conquerer, thou art general #Lord of kine for all, Thou Shaker of all things that be.\n\np: @Indra, whatever deed of #might thou hast this day to execute, None be there now to hinder it.\n\np: O Watchful One. May @Aryaman the @Deva.give thee all goodly things. May @Pusan, @Bhaga, and the @Deva.Karulati give all things fair.","people":["@Indra","@Vrtra","@Visnu","@Yadu","@Turvasa","@Mitra","@Varuna","@Maghavan","@Susna","@Susna","@Savitar","@Visnu","@Pusan","@Bhaga","@Kutsa","@Usas","@Etasa","@Deva","@Aryaman","@Turvasa","@Yadu"],"places":["$Heaven","$Sky"],"things":["#Lord","#Soma","#Waters","#Sun","#Stream","#Might","#Strong","#Mighty","#Car","#Heroes","#People","#Powers","#Bliss","#Death"],"groups":["#Devas","#Son","#Man"],"concepts":["Death","Heroic","Swift"],"hash":"md5-6LQaofPalByupnfqFmjhrg==","created":"Wednesday, November 22, 2023 - 6:01:42 AM"},{"id":"f4ba771b-5fc0-4cdc-85fb-92350427e1bb","key":"04031","book":"04","title":"HYMN XXXI. Indra.","link":"https://indra.ai/rigveda/hymns/04031.html","text":"p: WITH what #help will he come to us, wonderful, ever-waxing #Friend; With what most #mighty company?\n\np: What genuine and most liberal draught will #spirit thee with #juice to burst Open e’en strongly-guarded #wealth?\n\np: Do thou who art Protector of us thy #friends who #praise thee With hundred aids approach us.\n\np: Like as a courser's circling wheel, so turn thee hitherward to us, Attracted by the hymns of #men.\n\np: Thou seekest as it were thine own stations with swift descent of #powers: I share thee even with the #Sun.\n\np: What time thy courage and his wheels together, @Indra, run their course With thee and with the #Sun alike,\n\np: So even, #Lord of Power and #Might, the #people #call thee @Indra, @Indra, @Varuna, and @Mitra, #Soma, @Maghavan, @Savitar, @Visnu, Giver, who pauses not to think.\n\np: And verily to him who toils and presses #Soma #juice for thee Thou quickly givest ample #wealth.\n\np: No, not a hundred hinderers can check thy gracious bounty's #flow, Nor thy great deeds when thou wilt act.\n\np: May thine assistance keep us safe, thy hundred and thy thousand aids: May all thy favours strengthen us.\n\np: Do thou elect us this place for friendship and prosperity, and great celestial opulence.\n\np: Favour us, @Indra, evermore with overflowing store of #wealth: With all thy assists aid thou us.\n\np: With new protections, @Indra, like an archer, open thou for us The stables that are filled with kine.\n\np: Our chariot, @Indra, boldly moves endued with #splendour, ne’er repulsed, #Winning for us both kine and #steeds.\n\np: O @Surya, make our fame to be most #excellent among the #Devas, most lofty as the $Heaven on high.","people":["@Indra","@Visnu","@Mitra","@Varuna","@Maghavan","@Savitar","@Visnu","@Surya"],"places":["$Heaven"],"things":["#Steeds","#Lord","#Soma","#Sun","#Wealth","#Men","#Flow","#Might","#Juice","#Help","#Mighty","#Praise","#Splendour","#Excellent","#People","#Powers","#Friends","#Friend","#Winning","#call","#Spirit"],"groups":["#Devas"],"concepts":["Celestial","Friendship","Giver","Swift"],"hash":"md5-/YE3AMZdpFqooZFXrKi5wQ==","created":"Wednesday, November 22, 2023 - 6:01:42 AM"},{"id":"42cd0ee4-f4d6-4b54-b0b1-02fe8d7d01b8","key":"04032","book":"04","title":"HYMN XXXII. Indra.","link":"https://indra.ai/rigveda/hymns/04032.html","text":"p: O THOU who slewest @Vrtra, come, O @Indra, hither to our side, #Mighty One with thy #mighty aids.\n\np: Swift and impetuous art thou, wondrous amid the well-dressed folk: Thou doest marvels for our #help.\n\np: Even with the weak thou smitest down him who is stronger, with thy strength The #mighty, with the #Friends thou hast.\n\np: O @Indra, we are close to thee; to thee we sing aloud our #songs: #Help and defend us, even us.\n\np: As such, O @Indra, come with thy assists wonderful, Blameless, and irresistible.\n\np: May we be #friends of one like thee, O @Indra, with the #wealth of kine, Comrades for lively energy.\n\np: For thou, O @Indra, art alone the #Lord of strength that comes from kine So grant thou us abundant #food.\n\np: They turn thee not another way, when, lauded, Lover of the #Song, Thou wilt give #wealth to those who #praise.\n\np: The #Gotamas have sung their #song of #praise to thee that tho. Mayst give, @Indra, for lively energy.\n\np: We will declare thy #hero deeds, what Dasa forts thou brakest down, Attacking them in rapturous #joy.\n\np: The sages sing those manly deeds which, @Indra, Lover of the #Song, Thou wroughtest when the #Soma flowed.\n\np: @Indra, the #Gotamas who bring thee praises have grown #strong by thee. Give them renown with #hero #sons.\n\np: For, @Indra, verily thou art the general #treasure. even of all . Thee, therefore, do we invocate.\n\np: #Excellent @Indra, turn to us: glad thee among us with the #juice Of Somas, #Soma-drinker thou.\n\np: May #praise from us who think Qn thee, O @Indra, bring thee near to us. Turn thy two Bay #Steeds hitherward.\n\np: Eat of our #offerings cake: rejoice thee in the #songs we sing. Even as a lover in his bride.\n\np: To India for a thousand #steeds well-trained and fleet of foot we meditate, and hundred jars of #Soma #juice.\n\np: We make a hundred of thy kine, yea, and a thousand, hasten nigh: So let thy bounty come to us.\n\np: We have obtained, a #gift from thee, ten #water-ewers wrought of #gold: Thou, @Vrtra conquerer, givest much.\n\np: A bounteous Giver, give us much, bring much and not a trifling #gift: Much, @Indra, wilt thou fain bestow.\n\np: O @Vrtra conquerer, thou art famed in many a place as bountiful #Hero, thy bounty let us share.\n\np: I #praise thy pair of Tawny #Steeds, #wise #Son of him who giveth kine Terrify not the cows with these.\n\np: Like two slight images of girls, unrobed, upon a new-wrought post, So #shine the Bay #Steeds in their course.\n\np: For me the Bays are ready when I start, or start not, with the @Dawn, innocuous in the ways they take.","people":["@Indra","@Vrtra","@Dawn"],"places":[],"things":["#Steeds","#Lord","#Soma","#Water","#Shine","#Treasure","#Wealth","#Food","#Juice","#Song","#Joy","#Gold","#Help","#Wise","#Strong","#Mighty","#Praise","#Gift","#Excellent","#Offerings","#Friends","#Songs","#Hero"],"groups":["#Sons","#Gotamas","#Son"],"concepts":["Strength","Offerings","Giver","Swift"],"hash":"md5-GRFGWKT+9KDvfVHJC6Uauw==","created":"Wednesday, November 22, 2023 - 6:01:42 AM"},{"id":"6cda918e-3cd3-4172-8160-420a58366570","key":"04033","book":"04","title":"HYMN XXXIII. Rbhus.","link":"https://indra.ai/rigveda/hymns/04033.html","text":"p: I SEND my #voice as herald to the @Rbhus; I crave the white #cow for the overspreading. Wind-sped, the Skillful Ones in rapid motion have in an instant compassed round the $Heaven.\n\np: What time the Rbus had with care and marvels done proper service to assist their #Parents, they won the friendship of the #Devas; the Sages carried away the fruit of their devotion.\n\np: May they who made their #Parents, who were lying like posts that moulder, young again forever. May @Vaja, @Vibhvan, Rbhu, joined with @Indra , protect  'our #offering, the #Soma-lovers.\n\np: As for a year the @Rbhus kept the Milch-#cow, throughout a year fashioned and formed her body, and through a year's space still sustained her brightness, through these their labours they were made #immortal.\n\np: Two beakers let us make.thus said the eldest. Let us make three.this was the younger's sentence. Four beakers let us make.thus spoke the youngest. @Tvastar approved this rede of yours, O @Rbhus.\n\np: The #men spake truth and even so they acted: this Devalike way of theirs the @Rbhus followed. And @Tvastar, when he looked on the four beakers resplendent as the day, was moved with envy.\n\np: When for twelve days the @Rbhus joyed reposing as guests of him who neve. May be hidden, they made fair fertile fields, they brought the #rivers. Plants spread o’er deserts, #waters filled the hollows.\n\np: May they who formed the swift #car, bearing #Heroes, and the #Cow omniform and all-impelling, Eve. May they #form #wealth for us.the @Rbhus, dexterous-handed, deft in #work and gracious.\n\np: So in their #work the #Devas had satisfaction, pondering it with thought and mental insight. The #Devas’ expert artificer was @Vaja, @Indra's @Rbhuksan, @Varuna's was @Vibhvan.\n\np: They who made glad with #offering and praises, wrought the two Bays, his docile #Steeds, for @Indra. @Rbhus, as those who wish a #friend to prosper, bestow upon us gear and growth of #riches.\n\np: This day have they set gladdening drink before you. Not without toil are #Devas inclined to friendship. Therefore do ye who are so great, O @Rbhus, vouchsafe us #treasure.s at this third libation.","people":["@Indra","@Varuna","@Tvastar","@Rbhus","@Vibhvan","@Vaja","@Rbhuksan"],"places":["$Heaven"],"things":["#Steeds","#Work","#Rivers","#Soma","#Waters","#Offering","#Treasure","#Wealth","#Men","#Rivers","#Car","#Voice","#Heroes","#Form","#Offering","#Friend","#Cow","#Parents","#Riches"],"groups":["#Devas","#Immortal"],"concepts":["Friendship","Immortal","Offering","Truth","Swift"],"hash":"md5-SeYuPe1BekSIdhHdATw7fQ==","created":"Wednesday, November 22, 2023 - 6:01:42 AM"},{"id":"8d3f545c-4b78-4a1e-bf68-8b212d8ff8ca","key":"04034","book":"04","title":"HYMN XXXIV. Rbhus.","link":"https://indra.ai/rigveda/hymns/04034.html","text":"p: To this  'our #offering come Rbhu, @Vibhvan, @Vaja, and @Indra with the #gift of #riches, because this day hath @Dhisana the Devi set drink for you: the gladdening draughts have reached you.\n\np: Knowing your birth and rich in gathered #treasure., @Rbhus, rejoice together with the #Rtus. The gladdening draughts and wisdom have approached you: send ye us #riches with good store of #heroes.\n\np: For you was made this #offering, O @Rbhus, which ye, like #men, won for yourselves aforetime. To you come all who find in you their pleasure: ye all were—even the two elder—Vajas.\n\np: Now for the mortal #worshipper, O #Heroes, for him who served you, was the #gift of #riches. Drink, Vajas, @Rbhus! unto you is offered, to gladden you, the third and great libation.\n\np: Come to us. #Heroes, Vajas and Rbhuksans, glorified for the sake of #mighty #treasure.. These draughts approach you as the day is closing, as cows, whose calves are newly-#born, their stable.\n\np: Come to this #offering of ours, ye Children of Strength, invoked with #humble adoration. Drink of this #meath, #Wealth-givers, joined with @Indra with whom ye are in full accord, ye Princes.\n\np: Close knit with @Varuna drink the #Soma, @Indra; close-knit, #Hymn-lover! with the #Maruts drink it: Close-knit with drinkers first, who drink in season; close-knit with heavenly #Dames who give us #treasure.s.\n\np: Rejoice in full accord with the @Adityas, in concord with the #Parvatas, O @Rbhus; In full accord with @Indra, @Indra, @Varuna, and @Mitra, #Soma, @Maghavan, @Savitar, @Visnu, Divine One; in full accord with floods that pour forth #riches.\n\np: @Rbhus, who helped their #Parents and the @Asvins, who formed the Milch-#cow and the pair of #horses, Made armour, set the $Heaven and $Earth asunder.far- reaching #Heroes, they have made good #offspring.\n\np: Ye who have #wealth in booty, in #heroes, in rich sustenance and #treasure., Such, O ye @Rbhus, first to drink, rejoicing, give unto us and those who laud our present.\n\np: Ye were not far: we have not left you thirsting, blameless in this  'our #offering, O @Rbhus. Rejoice you with the #Maruts and with @Indra, with the #Kings, #Devas! that y. May give us #riches.","people":["@Indra","@Visnu","@Mitra","@Varuna","@Asvins","@Maghavan","@Rbhus","@Adityas","@Adityas","@Savitar","@Dhisana","@Visnu","@Vibhvan","@Vaja"],"places":["$Earth","$Heaven"],"things":["#Meath","#Born","#Soma","#Offering","#Treasure","#Wealth","#Men","#Humble","#Offspring","#Mighty","#Worshipper","#Hymn","#Heroes","#Gift","#Offering","#Cow","#Parents","#Horses","#Riches"],"groups":["#Devas","#Maruts","#Rtus","#Parvatas","#Kings","#Dames"],"concepts":["Good","Birth","Heavenly","Divine","Strength","Wisdom","Offering"],"hash":"md5-GYEEb7n4o6MIPxqdrJUWUg==","created":"Wednesday, November 22, 2023 - 6:01:42 AM"},{"id":"372f080a-1445-4eef-9c9a-a73ce1508cef","key":"04035","book":"04","title":"HYMN XXXV. Rbhus.","link":"https://indra.ai/rigveda/hymns/04035.html","text":"p: Come hither, O ye #Sons of Strength, ye @Rbhus; stay not afar, ye Children of Sudhanvan. At this libation is your #gift of #treasure.. Let gladdening draughts approach you after @Indra's.\n\np: Hither is come the @Rbhus' #gift of #riches; here was the drinking of the well-pressed #Soma, Since by dexterity and skill as craftsmen ye made the single chalice to be fourfold \n\np: Ye made fourfold the chalice that wag single: ye spake these words and said, O #Friend, assist us; Then, Vajas! gained the path of #life eternal, deft-handed @Rbhus, to the #Devas’ assembly.\n\np: Out of what substance was that chalice fashioned which ye made fourfold by your art and wisdom? Now for the gladdening draught press out the liquor, and drink, O @Rbhus, of die #meath of #Soma.\n\np: Ye with your cunning made your #Parents youthful; the cup, for #Devas to drink, ye formed with cunning; With cunning, @Rbhus, rich in #treasure., fashioned the two swift Tawny #Steeds who carry @Indra.\n\np: Whoso pours out for you, when days are closing, the sharp libation for your #joy, O Vajas, for him, O #mighty @Rbhus, ye, rejoicing, have fashioned #wealth with plenteous store of #heroes.\n\np: #Lord of Bay #Steeds, at @Dawn the #juice thou drankest: thine, only thine, is the noonday libation. Now drink thou with the #wealth-bestowing @Rbhus, whom for their skill thou madest #friends, O @Indra.\n\np: Ye, whom your artist skill hath raised to @Deva.ead have set you down above in $Heaven like falcons. So give us #riches, Children of Sudhanvan, O #Sons of Strength; ye have become #immortal.\n\np: The third libation, that bestoweth #treasure., which ye have won by skill, ye dexterous-handed. This drink hath been effused for you, O @Rbhus . drink it with high #delight, with #joy like @Indra's.","people":["@Indra","@Rbhus","@Deva","@Dawn"],"places":["$Heaven"],"things":["#Meath","#Steeds","#Lord","#Soma","#Treasure","#Wealth","#Juice","#Joy","#Mighty","#Delight","#Heroes","#Gift","#Friends","#Friend","#Parents","#Riches","#Life"],"groups":["#Devas","#Sons","#Immortal"],"concepts":["Life","Immortal","Strength","Wisdom","Swift"],"hash":"md5-G5ySFf31BXQRZ6Bk1FEPuA==","created":"Wednesday, November 22, 2023 - 6:01:42 AM"},{"id":"8fc352a5-4c8c-492c-9fb8-1f16f040167c","key":"04036","book":"04","title":"HYMN XXXVI. Rbhus.","link":"https://indra.ai/rigveda/hymns/04036.html","text":"p: THE #car that was not made for #horses or for reins, three-wheeled, worthy of lauds, rolls round the $Firmament. That is the great announcement of your Deity, that, O ye @Rbhus, ye sustain the $Earth and $Heaven.\n\np: Ye Sapient Ones who made the lightly-rolling #car out of your mind, by thought, the #car that never errs, You, being such, to drink of this drink-#offering, you, O ye Vajas, and ye @Rbhus, we invoke.\n\np: O Vajas, @Rbhus, reaching far, among the #Devas this was your exaltation gloriously declared, in that your aged #Parents, worn with length of days, ye wrought again to youth so that they moved at will.\n\np: The chalice that wag single ye have made fourfold, and by your wisdom brought the #Cow forth from the hide. So quickly, mid the #Devas, ye gained #immortal #life. Vajas and @Rbhus, your great #work must be extolled.\n\np: #Wealth from the @Rbhus is most #glorious in renown, that which the #Heroes, famed for vigour, have produced. In synods must be sung the #car which @Vibhvan wrought: that which ye favour, #Devas! is famed among #mankind.\n\np: #Strong is the steed, the #man a #sage in eloquence, the bowman is a #hero hard to beat in fight, Great store of #wealth and manly power hath he obtained whom @Vaja, @Vibhvan, @Rbhus have looked kindly on.\n\np: To you hath been assigned the fairest ornament, the #hymn of #praise: Vajas and @Rbhus, #joy therein; For ye have lore and wisdom and poetic skill: as such, with this our #meditation we #call on you to come.\n\np: According to the wishes of our heart. May ye, who have full knowledge of all the delights of #men, Fashion for us, O @Rbhus, power and splendid #wealth, rich in high courage, #excellent, and vital strength.\n\np: Bestowing on us here #riches and #offspring, here fashion fame for us befitting #heroes. Vouchsafe us #wealth of splendid sort, O @Rbhus, that we may make us more renowned than others.","people":["@Rbhus","@Vibhvan","@Vaja"],"places":["$Earth","$Heaven","$Firmament"],"things":["#Mankind","#Work","#Mankind","#Meditation","#Glorious","#Offering","#Wealth","#Men","#Joy","#Offspring","#Strong","#Car","#Praise","#Hymn","#Heroes","#Excellent","#Offering","#Hero","#Sage","#Cow","#Parents","#Horses","#call","#Riches","#Life"],"groups":["#Devas","#Immortal","#Man"],"concepts":["Life","Immortal","Strength","Wisdom","Offering","Glorious"],"hash":"md5-3nilm9cT7X/FrhXBmkxPHQ==","created":"Wednesday, November 22, 2023 - 6:01:42 AM"},{"id":"2d4bb095-31ea-4420-b014-2a0228105a20","key":"04037","book":"04","title":"HYMN XXXVII. Rbhus.","link":"https://indra.ai/rigveda/hymns/04037.html","text":"p: COME to  'our #offering, Vajas, Rbhuksans, #Devas, by the paths which #Devas are wont to travel, as ye, gay #Devas, accept in splendid weather  'the #offering among these folk of Manus.\n\np: May these rites please you in your heart and #spirit. May the #drops clothed in oil this day approach you. May the abundant juices bear you onward to power and strength, and, when imbibed, #delight you.\n\np: Your threefold going near is @Deva.appointed, so #praise is given you, Vajas and Rbhuksans. So, Manus-like, mid younger folk I offer, to you who are aloft in $Heaven, the #Soma.\n\np: #Strong, with fair chains of #gold and jaws of iron, ye have a splendid #car and well-fed #horses. Ye #Sons of Strength, ye #progeny of @Indra, to you the best is offered to #delight you.\n\np: Rbhuksans! him, for handy #wealth, the mightiest comrade in the fighthim, @Indra's equal, we invoke, most bounteous ever, rich in #steeds.\n\np: The mortal #man whom, @Rbhus, ye and @Indra favour with your #help, Must be successful, by his thoughts, at #offering and with the steed.\n\np: O Vajas and Rbhuksans, free for us the paths to #offering, Ye Princes, lauded, that we may press forward to each point of $Heaven.\n\np: O Vajas and Rbhuksans, ye @Nasatyas, @Indra, bless this #wealth, and, before other #men's, the steed, that ample riche. May be won.","people":["@Indra","@Nasatyas","@Rbhus","@Deva"],"places":["$Heaven"],"things":["#Steeds","#Soma","#Offering","#Wealth","#Men","#Gold","#Help","#Strong","#Car","#Praise","#Delight","#Offering","#Drops","#Horses","#Spirit"],"groups":["#Devas","#Sons","#Progeny","#Man"],"concepts":["Strength","Offering"],"hash":"md5-Hi00IyvpD16qSpn6PIbFKw==","created":"Wednesday, November 22, 2023 - 6:01:42 AM"},{"id":"ef82903d-0b53-4c51-ac28-990e7d83dc39","key":"04038","book":"04","title":"HYMN XXXVIII. Dadhikris.","link":"https://indra.ai/rigveda/hymns/04038.html","text":"p: FROM you two came the #gifts in days aforetime which Trasadasyu granted to the Purus. Ye gave the winner of our fields and plough-lands, and the #strong smiter who subdued the #Dasyus.\n\np: And ye gave #mighty #Dadhikras, the giver of many #gifts, who visiteth all #people, Impetuous hawk, swift and of varied colour, like a #brave #King whom each true #man must honour.\n\np: Whom, as ’twere down a precipice, swift rushing, each Puru praises and his heart rejoices. Springing forth like a #hero fain for battle, whirling the #car and flying like the tempest.\n\np: Who gaineth precious booty in the combats and moveth, #winning #spoil, among the #cattle; Shown in bright colour, looking on the assemblies, beyond the churl, to #worship of the living.\n\np: Loudly the folk cry after him in battles, as ’twere a thief who steals away a garment; Speeding to #glory, or a herd of #cattle, even as a hungry falcon swooping downward.\n\np: And, fain to come forth first amid these #armies, this way and that with rows of #cars he rushes, Gay like a bridesman, making him a garland, tossing the dust, champing the rein that holds him.\n\np: And that #strong Steed, victorious and faithful, obedient with his body in the combat, Speeding straight on amid the swiftly pressing, casts o’er his brows the dust he tosses upward.\n\np: And at his thunder, like the roar of $Heaven, those who attack tremble and are affrighted; For when he fights against embattled thousands, dread is he in his striving; non. May stay him.\n\np: The #people #praise the overpowering swiftness of this fleet Steed who giveth #men abundance. Of him they say when drawing back from battle. #Dadhikras hath sped forward with his thousands.\n\np: #Dadhikras hath o’erspread the Fivefold #People with vigour, as the #Sun lightens the #waters. May the #strong Steed who winneth hundreds, thousands, requite with sweetness these my words and praises.","people":[],"places":["$Heaven"],"things":["#Worship","#Waters","#Glory","#Sun","#Men","#Strong","#Mighty","#Car","#Armies","#Praise","#Brave","#People","#Worship","#Hero","#King","#Winning","#spoil","#Cars","#Cattle","#Gifts"],"groups":["#Dasyus","#Dadhikras","#Man"],"concepts":["Cars","Giver","Swift","Winner"],"hash":"md5-HdrV2CjHI2hpHl3S9sLK2g==","created":"Wednesday, November 22, 2023 - 6:01:42 AM"},{"id":"884f5288-7982-4431-abaa-72b7032d8a33","key":"04039","book":"04","title":"HYMN XXXIX Dadhikras.","link":"https://indra.ai/rigveda/hymns/04039.html","text":"p: Now give we #praise to #Dadhikras the rapid, and mention in our laud the $Earth and $Heaven. May the #Dawns flushing move me to exertion, and bear me safely over every trouble.\n\np: I #praise the #mighty Steed who fills my #spirit, the Stallion @Dadhikravan rich in bounties, whom, swift of foot and shining bright as @Agni, ye, @Varuna and @Mitra, gave to Purus.\n\np: Him who hath honoured, when the flame is kindled at break of @Dawn, the Courser Dadhikravanhim, of one mind with @Varuna and Mitr. May @Aditi make free from all transgression.\n\np: When we remember #mighty @Dadhikravan our #food and strength, then the blest name of #Maruts, @Varuna, @Mitra, we invoke for welfare, and @Agni, and the thunder-wielding @Indra.\n\np: Both sides invoke him as they #call on @Indra when they stir forth and turn to sacrificing. To us have @Varuna and @Mitra granted the Courser #Dadhikras, a guide for mortals.\n\np: So have I glorified with #praise #strong @Dadhikravan, conquering Steed. Swee. May he make our mouths. May he prolong the days we have to live.","people":["@Indra","@Agni","@Mitra","@Varuna","@Dawn","@Aditi","@Dadhikravan"],"places":["$Earth","$Heaven"],"things":["#Food","#Strong","#Mighty","#Praise","#call","#Spirit"],"groups":["#Maruts","#Dawns","#Dadhikras"],"concepts":["Strength","Swift"],"hash":"md5-msxNTnt6Hgc6Z7mJ4i5I5w==","created":"Wednesday, November 22, 2023 - 6:01:42 AM"},{"id":"ccba4597-abf3-4d4e-b76e-e824c22c7d91","key":"04040","book":"04","title":"HYMN XL. Dadhikravan.","link":"https://indra.ai/rigveda/hymns/04040.html","text":"p: LET us recite the #praise of @Dadhikravan. May all the Mornings move me to exertion; #Praise of the #Lord of #Waters, @Dawn, and @Agni, @Narasamsa #Son of @Angiras, and @Surya.\n\np: #Brave, seeking war and booty, dwelling with the good and with the swift. May he hasten the #food of @Dawn. May he the true, the fleet, the lover of the course, the #bird-like @Dadhikravan, bring #food, strength, and #light.\n\np: His pinion, rapid runner, fans him m his way, as of a #bird that hastens onward to its aim, and, as it were a falcon's gliding through the #air, strikes @Dadhikravan's side as he speeds on with #might.\n\np: Bound by the neck and by the flanks and by the mouth, the vigorous Courser lends new swiftness to his speed. Drawing himself together, as his strength allows, #Dadhikras springs along the windings of the paths.\n\np: The Hamsa homed in #light, the @Vasu in $$Mid-#Air, the #Sage beside the altar, in the house the guest, Dweller in noblest place, mid #men, in truth, in $Sky, #born of flood, kine, truth, mountain, he is holy Law.","people":["@Agni","@Angiras","@Narasamsa","@Surya","@Dawn","@Dadhikravan","@Vasu"],"places":["$Mid-Air","$Sky","$Mid-Air"],"things":["#Lord","#Born","#Waters","#Light","#Air","#Food","#Men","#Might","#Praise","#Brave","#Bird","#Sage"],"groups":["#Son","#Dadhikras"],"concepts":["Good","Holy","Strength","Truth","Swift"],"hash":"md5-TmfOE5ksWXqZB87kbP9r4w==","created":"Wednesday, November 22, 2023 - 6:01:42 AM"},{"id":"69b13525-5cac-4e0d-9cdd-def595bd3248","key":"04041","book":"04","title":"HYMN XLI. Indra-Varuna.","link":"https://indra.ai/rigveda/hymns/04041.html","text":"p: WHAT laud, O @Indra-@Varuna, with oblation, hath like the #Immortal Monk obtained your favour? Hath our effectual laud, addressed with homage, touched you, O @Indra-@Varuna, in #spirit?\n\np: He who with dainty #food hath won you, @Indra and @Varuna, #Devas, as his allies to friendship, Slayeth the #Vrtras and his foes in battles, and through your #mighty favours is made famous.\n\np: @Indra and @Varuna are most liberal givers of #treasure. to the #men who toil to serve them, when they, as #Friends inclined to friendship, honoured with dainty #food, #delight in flowing #Soma.\n\np: @Indra and @Varuna, ye hurl, O #Mighty, on him your strongest flashing bolt of thunder Who treats us ill, the robber and oppressor: measure on him your overwhelming vigour.\n\np: O @Indra-@Varuna, be ye the lovers of this my #song, as #steers who love the milch-#Cow. Mil. May it yield us as, gone forth to pasture, the great #Cow pouring out her thousand #rivers.\n\np: For fertile fields, for worthy #sons and grandsons, for the #Sun's #beauty and for steer-like vigour, may @Indra-@Varuna with gracious favours #work marvels for us in the stress of battle.\n\np: For you, as Princes, for your ancient kindness, good comrades of the #man who seeks for booty, We choose to us for the dear bond of friendship, most liberal #Heroes bringing #bliss like #parents.\n\np: Showing their strength, these hymns for grace, free-givers I have gone to you, devoted, as to battle. For #glory have they gone, as #milk to #Soma, to @Indra-@Varuna my thoughts and praises.\n\np: To @Indra and to @Varuna, desirous of gaining #wealth have these my thoughts proceeded. They have come nigh to you as #treasure.-lovers, like mares, fleet-footed, eager for the #glory.\n\np: May we ourselves be lords of during #riches, of ample sustenance for #car and hones. May the Twain who #work with newest assists bring yoked teams hitherward to us and #riches.\n\np: Come with your #mighty assists, O ye #Mighty; come, @Indra-@Varuna, to us in battle. What time the flashing arrows play in combat. May we through you be winners in the contest.","people":["@Indra","@Varuna"],"places":[],"things":["#Milk","#Work","#Rivers","#Soma","#Glory","#Sun","#Treasure","#Wealth","#Food","#Men","#Rivers","#Song","#Beauty","#Mighty","#Car","#Delight","#Heroes","#Friends","#Bliss","#Cow","#Parents","#Riches","#Spirit"],"groups":["#Devas","#Sons","#Steers","#Immortal","#Man","#Vrtras"],"concepts":["Good","Friendship","Love","Immortal","Strength"],"hash":"md5-mSKS1fLwfD3/AEmHFUT/DA==","created":"Wednesday, November 22, 2023 - 6:01:42 AM"},{"id":"2bcf0d10-d65c-4d45-a276-2482620b5332","key":"04042","book":"04","title":"HYMN XLIL Indra-Varuna.","link":"https://indra.ai/rigveda/hymns/04042.html","text":"p: I AM the royal Ruler, mine is empire, as mine who sway all #life are all Immortals. @Varuna's will the #Devas obey and follow. I am the #King of #men's most lofty cover.\n\np: I am #King @Varuna. To me were given these first existing high celestial #powers. @Varuna's will the #Devas obey and follow. I am the #King of #men's most lofty cover.\n\np: I @Varuna am @Indra: in their greatness, these the two wide deep fairly-fashioned regions, these the two world-halves have I, even as @Tvastar knowing all beings, joined and held together.\n\np: I made to #flow the moisture-shedding #waters, and set the $Heaven firm in the scat of #Order. By Law the #Son of @Aditi, Law Observer, hath spread abroad the world in threefold measure.\n\np: #Heroes with noble #horses, fain for battle, selected warriors, #call on me in combat. I @Indra @Indra, @Indra, @Varuna, and @Mitra, #Soma, @Maghavan, @Savitar, @Visnu, excite the conflict; I stir the dust, #Lord of surpassing vigour.\n\np: All this I did. The #Devas’ own conquering power never impedeth me whom none opposeth. When lauds and #Soma #juice have made me joyful, both the unbounded regions are affrighted.\n\np: All beings know these deeds of thine thou tellest this unto @Varuna, thou great Disposer! Thou art renowned as having slain the #Vrtras. Thou madest #flow the floods that were obstructed.\n\np: Our #fathers then were these, the Seven his, what time the #son of Durgaha was captive. For her they gained by #offering Trasadasyu, a demi-god, like @Indra, conquering foemen.\n\np: The #spouse of Purukutsa gave oblations to you, O @Indra-@Varuna, with homage. Then unto her ye gave #King Trasadasyu, the demi-god, the slayer of the foeman.\n\np: May we, possessing much, #delight in #riches, #Devas in oblations and the kine in pasture; And that Milch-#cow who shrinks not from the milking, O @Indra-@Varuna, give to us daily.","people":["@Indra","@Visnu","@Mitra","@Varuna","@Maghavan","@Tvastar","@Savitar","@Visnu","@Aditi"],"places":["$Heaven"],"things":["#Lord","#Soma","#Waters","#Offering","#Men","#Flow","#Juice","#Delight","#Heroes","#Powers","#Offering","#King","#Cow","#Horses","#call","#Riches","#Spouse","#Order","#Life"],"groups":["#Devas","#Fathers","#Son","#Vrtras"],"concepts":["Celestial","Life","Offering","Noble"],"hash":"md5-f0+jlG8VcV7D20tXS1piJA==","created":"Wednesday, November 22, 2023 - 6:01:42 AM"},{"id":"179bebf7-e83f-462c-b8dd-bdb1fb91fc7c","key":"04043","book":"04","title":"HYMN XLIII. Asvins.","link":"https://indra.ai/rigveda/hymns/04043.html","text":"p: WHO will hear, who of those who merit #worship, which of all #Devas take pleasure in our homage? On whose heart shall we lay this laud celestial, rich with fair #offerings, dearest to Immortals?\n\np: Who will be gracious? Who will come most quickly of all the #Devas? Who will bring #bliss most largely? What #car do they #call swift with rapid coursers? That which the Daughter of the #Sun elected.\n\np: So many days do ye come swiftly hither, as @Indra to give #help in stress of battle. Descended from the $Sky, divine, #strong-pinioned, by which of all your #powers are ye most #mighty?\n\np: What is the prayer that we should bring you, @Asvins, whereby ye come to us when invocated? Whether of you confronts e’en great betrayal? Lovers of sweetness, Dasras, #help and save us.\n\np: In the wide space your chariot reacheth $Heaven, what time it turneth hither from the $Ocean. Sweets from your sweet shall drop, lovers of sweetness! These have they dressed for you as dainty #offerings.\n\np: Let @Sindhu with his wave bedew your #horses: in fiery glow have the red birds come hither. Observed of all was that your rapid going, whereby ye were the Lords of @Surya's Daughter.\n\np: Whene’er I gratified you here together, your grace was given us, O ye rich in booty. Protect, ye Twain, the #singer of your praises: to you, @Nasatyas, is my wish directed.","people":["@Indra","@Asvins","@Nasatyas","@Surya","@Sindhu"],"places":["$Ocean","$Heaven","$Sky"],"things":["#Worship","#Singer","#Sun","#Help","#Strong","#Mighty","#Car","#Worship","#Powers","#Offerings","#Bliss","#Horses","#call"],"groups":["#Devas"],"concepts":["Celestial","Divine","Offerings","Swift"],"hash":"md5-i0Gvi/EtUPI31mQNATlnhg==","created":"Wednesday, November 22, 2023 - 6:01:43 AM"},{"id":"f14beb91-2e17-497a-a2b1-376a52ee7870","key":"04044","book":"04","title":"HYMN XLIV. Asvins.","link":"https://indra.ai/rigveda/hymns/04044.html","text":"p: WE will invoke this day your #car, far-spreading, O @Asvins, even the gathering, of the sunlight. #Car praised in hymns, most ample, rich in #treasure., fitted with seats, the #car that beareth @Surya.\n\np: @Asvins, ye gained that #glory by your @Deva.ead, ye #Sons of $Heaven, by your own #might and power. #Food followeth close upon your bright appearing when stately #horses in your chariot draw you.\n\np: Who bringeth you to-day for #help with offered oblation, or with hymns to drink the juices? Who, for  'the #offering's ancient lover, turneth you hither, @Asvins, #offering homage?\n\np: Borne on your golden #car, ye omnipresent! come to this #offering of ours, @Nasatyas. Drink of the pleasant liquor of the #Soma give #riches to the #people who adore you.\n\np: Come hitherward to us from $Earth, from $Heaven, borne on your golden chariot rolling lightly. Suffer not other #worshippers to stay you here are ye bound by earlier bonds of friendship.\n\np: Now for us both, mete out, O Wonder-Workers, #riches exceeding great with store of #heroes, because the #men have sent you #praise, O @Asvins, and @Ajamilhas come to the laudation.\n\np: Whene’er I gratified you here together, your grace was given us, O ye rich in booty. Protect, ye Twain, the #singer of your praises: to you, @Nasatyas, is my wish directed.","people":["@Asvins","@Nasatyas","@Deva","@Surya","@Ajamilhas"],"places":["$Earth","$Heaven"],"things":["#Soma","#Glory","#Singer","#Offering","#Treasure","#Food","#Men","#Might","#Help","#Car","#Praise","#Heroes","#People","#Offering","#Horses","#Riches"],"groups":["#Sons","#Worshippers"],"concepts":["Wonder-Workers","Friendship","Golden Chariot Rolling Lightly","Offering"],"hash":"md5-PmzAvglNJkr5oVqRQHyQ7g==","created":"Wednesday, November 22, 2023 - 6:01:43 AM"},{"id":"48b14531-570f-49bd-8b46-ef50fd9a7d56","key":"04045","book":"04","title":"HYMN XLV. Asvins","link":"https://indra.ai/rigveda/hymns/04045.html","text":"p: YONDER goes up that #light: your chariot is yoked that travels round upon the summit of this $Heaven. Within this #car are stored three kindred shares of #food, and a skin filled with #meath is rustling as the fourth.\n\np: Forth come your #offerings rich with store of pleasant #meath, and #cars and #horses at the flushing of the @Dawn, Stripping the covering from the surrounded gloom, and spreading through $$Mid-#Air bright radiance like the #Sun.\n\np: Drink of the #meath with lips accustomed to the draught; harness for the #meath's sake the chariot that ye love. Refresh the way ye go, refresh the paths with #meath: hither, O @Asvins, bring the skin that holds the #meath.\n\np: The #swans ye have are friendly, rich in store of #meath, #gold-pinioned, #strong to draw, awake at early morn, Swimming the flood, exultant, fain for draughts that #cheer: ye come like flies to our #libations of the #meath.\n\np: Well knowing solemn rites and rich in #meath, the fires sing to the #morning @Asvins at the break of day, when with pure hands the prudent energetic priest hath with the stones pressed out the #Soma rich in #meath.\n\np: The rays advancing nigh, chasing with day the gloom, spread through the $Firmament bright radiance like the #Sun; And the #Sun harnessing his #horses goeth forth: ye through your @Deva.ike nature let his paths be known.\n\np: Devout in thought I have declared, O @Asvins, your chariot with good #steeds, which lasts forever, Wherewith ye travel swiftly through the regions to the prompt #worshipper who brings oblation.","people":["@Asvins","@Deva","@Dawn"],"places":["$Heaven","$Firmament","$Mid-Air","$Mid-Air"],"things":["#Meath","#Cheer","#Steeds","#Soma","#Light","#Air","#Sun","#Food","#Gold","#Strong","#Car","#Worshipper","#Offerings","#Libations","#Swans","#Horses","#Cars","#Morning"],"groups":[],"concepts":["Good","Travel Swiftly","Cars","Love","Devout","Offerings","Libations"],"hash":"md5-3RnTV0TpKkMhnc2ikJt4uQ==","created":"Wednesday, November 22, 2023 - 6:01:43 AM"},{"id":"fb4e42ba-740c-4914-aaab-d95199c45c86","key":"04046","book":"04","title":"HYMN XLVI. Vayu. Indra and Vayu","link":"https://indra.ai/rigveda/hymns/04046.html","text":"p: DRINK the best draught of #Soma-#juice, O @Vayu, at our holy rites: For thou art he who drinketh first.\n\np: Come, team-drawn, with thy hundred helps, with @Indra, seated in the #car, @Vayu, and drink your fill of #juice.\n\np: May #steeds a thousand bring you both, @Indra. and @Vayu, hitherward #Soma, to the feast.\n\np: For ye, O @Indra and @Vayu, mount the golden-seated #car that aids The #offering, that reaches $Heaven.\n\np: On far-refulgent chariot come unto the #man who #offers #gifts: Come, @Indra and @Vayu, hitherward.\n\np: Here, @Indra and @Vayu, is the #juice: drink it, accordant with the #Devas, within the giver's dwelling-place.\n\np: Hither, O @Indra and @Vayu, be your #journey here unyoke your #steeds. Here for your draught of #Soma #juice.","people":["@Indra","@Vayu"],"places":["$Heaven"],"things":["#Journey","#Steeds","#Soma","#Offering","#Juice","#Car","#Offers","#Offering","#Gifts"],"groups":["#Devas","#Man"],"concepts":["Holy","Offering","Giver"],"hash":"md5-cTlzN7k4CKaX9X+El/LOgg==","created":"Wednesday, November 22, 2023 - 6:01:43 AM"},{"id":"6f070277-fa4a-4a54-a95e-5292824be54f","key":"04047","book":"04","title":"HYMN XLVIL Vayu. Indra and Vayu.","link":"https://indra.ai/rigveda/hymns/04047.html","text":"p: @Vayu, the bright is offered thee, best of the #meath at holy rites. Come thou to drink the #Soma #juice, @Deva, longed-for, on thy team-drawn #car.\n\np: O @Vayu, thou and @Indra are meet drinkers of these #Soma-draughts, for unto you the #drops proceed as #waters gather to the vale.\n\np: O @Indra and @Vayu, #mighty Twain, speeding together, Lords of Strength, Come to our assist with your team, that y. May drink the #Soma #juice.\n\np: The longed-for teams which ye possess, O #Heroes, for the #worshipper, Turn to us, @Indra and @Vayu, ye to whom  'the #offering is paid.","people":["@Indra","@Vayu","@Deva"],"places":[],"things":["#Meath","#Soma","#Waters","#Offering","#Juice","#Mighty","#Car","#Worshipper","#Heroes","#Offering","#Drops"],"groups":[],"concepts":["Holy","Strength","Offering"],"hash":"md5-zLBkrwY9e5QT0ojWXDnkvQ==","created":"Wednesday, November 22, 2023 - 6:01:43 AM"},{"id":"36b30de2-ea33-4bea-90d2-98e7a241b260","key":"04048","book":"04","title":"HYMN XLVIII. Vayu.","link":"https://indra.ai/rigveda/hymns/04048.html","text":"p: TASTE #offerings never tasted yet, as bards enjoy the foeman's #wealth. O @Vayu, on refulgent #car come to the drinking of the #juice.\n\np: Removing curses, drawn by teams, with @Indra, seated by thy side, O @Vayu, on refulgent #car come to the drinking of the #juice.\n\np: The two dark #treasure.es of #wealth that wear all beauties wait on thee. O @Vayu, on refulgent #car come to the drinking of the #juice.\n\np: May nine-and-ninety harnessed #steeds who yoke them at thy will bring thee. O @Vayu, on refulgent #car come to the drinking of the #juice.\n\np: Harness, O @Vayu, to thy #car a hundred well-fed tawny #steeds, Yea, or a thousand #steeds, and let thy chariot come to us with #might.","people":["@Indra","@Vayu"],"places":[],"things":["#Steeds","#Treasure","#Wealth","#Might","#Juice","#Car","#Offerings"],"groups":[],"concepts":["Offerings"],"hash":"md5-gjt1U67wzbSlkRYEKXk/4w==","created":"Wednesday, November 22, 2023 - 6:01:43 AM"},{"id":"2103e24a-5675-4475-abcd-6a2c61808121","key":"04049","book":"04","title":"HYMN XLIX. Indra-Narasamsa.","link":"https://indra.ai/rigveda/hymns/04049.html","text":"p: DEAR is this #offering in your mouth, O @Indra and @Narasamsa: Famed is the laud, the gladdening draught.\n\np: This lovely #Soma is effused, O @Indra and @Narasamsa, for you, to drink it and rejoice.\n\np: As #Soma-drinkers to our house come, @Indra and @Narasamsa-and @Indra-to drink #Soma #juice.\n\np: Vouchsafe us #riches hundredfold, O @Indra, and @Narasamsa, with store of #horses, thousandfold.\n\np: O @Indra. and @Narasamsa, we #call you when the #meath is shed, with #songs, to drink the #Soma #juice.\n\np: Drink, @Indra and @Narasamsa, the #Soma in the giver's house: #Delight yourselves abiding there.","people":["@Indra","@Narasamsa"],"places":[],"things":["#Meath","#Soma","#Offering","#Juice","#Delight","#Offering","#Songs","#Horses","#call","#Riches"],"groups":[],"concepts":["Offering","Giver"],"hash":"md5-JqtQGAaRAUFN+r42L+5wuw==","created":"Wednesday, November 22, 2023 - 6:01:43 AM"},{"id":"fa0bbccb-1077-4338-a231-94b82208a9a8","key":"04050","book":"04","title":"HYMN L. Narasamsa.","link":"https://indra.ai/rigveda/hymns/04050.html","text":"p: Him who with #might hath propped $Earth's ends, who sitteth in threefold seat, @Narasamsa, with thunderhim of the pleasant tongue have ancient sages, deep-thinking, holy singers, set before them.\n\np: Wild in their course, in well-marked #wise rejoicing were they, @Narasamsa, who pressed around us. Preserve @Narasamsa, the stall uninjured, this company's raining, ever-moving birthplace.\n\np: @Narasamsa, from thy remotest distance have they sat down who love the #law eternal. For thee were dug wells springing from the mountain, which murmuring round about pour #streams of sweetness.\n\np: @Narasamsa, when first he had his being from #mighty #splendour in supremest $Heaven, #Strong, with his sevenfold mouth, with noise of thunder, with his seven rays, blew and dispersed the darkness.\n\np: With the loud-shouting band who sang his praises, with thunder, he conquered obstructive Vala. @Narasamsa thundering drave forth the #cattle, the lowing cows who make oblations ready.\n\np: Serve we with #offers, #gifts, and homage even thus the Steer of all the #Devas, the #Father. @Narasamsa. May we be lords of #riches, with noble #progeny and store of #heroes.\n\np: Surely that #King by power and #might heroic hath made him #lord of all his foes' posses-ions, who cherishes @Narasamsa well-tended, adorns and worships him as foremost sharer.\n\np: In his own house he dwells in peace and comfort: to him forever holy #food flows richly. To him the #people with free will pay homage-the #King with whom the Brahman hath precedence.\n\np: He, unopposed, is #master of the #riches of his own subjects and of hostile #people. The #Devas uphold that #King with their protection who helps the Brahman when he seeks his favour.\n\np: @Indra, @Narasamsa, rainers of #treasure., rejoicing at this #offering drink the #Soma. Let the abundant #drops sink deep within you: vouchsafe us #riches with full store of #heroes.\n\np: @Narasamsa and @Indra, make us prospe. May this be your benevolence to us-ward. Assist our holy thoughts, wake up our #spirit: weaken the hatred of our foe and rivals.","people":["@Indra","@Narasamsa"],"places":["$Earth","$Heaven"],"things":["#Master","#Lord","#Soma","#Law Eternal","#Offering","#Treasure","#Food","#Streams","#Might","#Wise","#Strong","#Mighty","#Heroes","#Splendour","#Offers","#People","#Offering","#Drops","#King","#Riches","#Cattle","#Spirit","#Gifts"],"groups":["#Devas","#Father","#Progeny"],"concepts":["Heroic","Love","Holy","Offering","Benevolence","Noble"],"hash":"md5-ZXZN3Phj7Cn413C7Xetjzg==","created":"Wednesday, November 22, 2023 - 6:01:43 AM"},{"id":"9674ebf9-d7f9-4c6f-89b1-9736ac9c5783","key":"04051","book":"04","title":"HYMN LI. Dawn.","link":"https://indra.ai/rigveda/hymns/04051.html","text":"p: FORTH from the darkness in the region eastward this most abundant splendid #light hatb mounted. Now verily the far-refulgent Mornings, Daughters of $Heaven, bring welfare to the #people.\n\np: The richly-coloured #Dawns have mounted eastward, like pillars planted at  'our #offerings, and, flushing far, splendid and purifying, unbarred the portals of the fold of darkness.\n\np: Dispelling gloom this day the wealthy Mornings urge liberal givers to present their #treasure.s. In the unlightened depth of darkness round them let niggard traffickers sleep unawakened.\n\np: O Devis, is this your #car, I ask you, ancient this day, or is it new, ye Mornings, Wherewith, rich #Dawns, ye seek with #wealth Navagva, Dasagva Angira, the seven-toned #singer?\n\np: With #horses harnessed by eternal #Order, Devis, swiftly round the worlds ye travel, Arousing from their rest, O #Dawns, the sleeping, and all that lives, #man, #bird, and beast, to motion.\n\np: Which among these is eldest, and where is she through whom they fixed the @Rbhus' regulations? What time the splendid #Dawns go forth for #splendour, they are not known apart, alike, unwasting.\n\np: Blest were these #Dawns of old, shining with assist, true with the truth that springs from holy #Order; With whom the toiling #worshipper, by praises, hymning and lauding, soon attained to #riches.\n\np: Hither from eastward all at once they travel, from one place spreading in the selfsame manner. Awaking, from the seat of holy #Order the @Deva.ike #Dawns come nigh like troops of #cattle.\n\np: Thus they go forth with undiminished colours, these Mornings similar, in self-same fashion, Concealing the gigantic #might of darkness with radiant bodies bright and pure and shining.\n\np: O Devis, O $Heaven's refulgent Daughters, bestow upon us #wealth with store of children. As from our pleasant place of rest ye rouse u. May we be #masters of heroic vigour.\n\np: Well-skilled in lore of #offering, ye Daughters of $Heaven, refulgent #Dawns, I thus address you. May we be #glorious among the #people. May $Heaven vouchsafe us this, and $Earth the Devi,","people":["@Rbhus","@Deva"],"places":["$Earth","$Heaven"],"things":["#Masters","#Glorious","#Singer","#Offering","#Light","#Treasure","#Wealth","#Might","#Car","#Worshipper","#Splendour","#People","#Offerings","#Offering","#Bird","#Horses","#Riches","#Order","#Cattle"],"groups":["#Dawns","#Man"],"concepts":["Heroic","Holy","Offering","Offerings","Truth","Glorious"],"hash":"md5-waJLYEi/76xNhAiLnJOHkw==","created":"Wednesday, November 22, 2023 - 6:01:43 AM"},{"id":"126a1dbb-1458-478d-8ce6-4c504cada313","key":"04052","book":"04","title":"HYMN LII. Dawn.","link":"https://indra.ai/rigveda/hymns/04052.html","text":"p: THIS Lady, giver of #delight, after her #Sister shining forth, Daughter of $Heaven, hath shown herself.-\n\np: Unfailing, #Mother of the Kine, in colour like a bright red mare, the @Dawn became the @Asvins' #Friend.\n\np: Yea, and thou art the @Asvins' #Friend, the #Mother of the Kine art thou: O @Dawn thou rulest over #wealth.\n\np: Thinking of thee, O joyous One, as her who driveth hate away, We woke to meet thee with our lauds.\n\np: Our eyes behold thy blessed rays like troops of #cattle loosed to feed. @Dawn hath filled full the wide expanse.\n\np: When thou hast filled it, Fulgent One! thou layest bare the gloom with #light. After thy nature aid us, @Dawn.\n\np: Thou overspreadest $Heaven with rays, the dear wide region of $$Mid-#Air. With thy bright shining lustre, @Dawn.","people":["@Asvins","@Dawn"],"places":["$Heaven","$Mid-Air","$Mid-Air"],"things":["#Light","#Air","#Wealth","#Delight","#Friend","#Cattle"],"groups":["#Mother","#Sister"],"concepts":["Giver"],"hash":"md5-C6d1zsOEiRnA1FnYPsdAaQ==","created":"Wednesday, November 22, 2023 - 6:01:43 AM"},{"id":"958ee016-eb84-4897-a725-ae47d5344adb","key":"04053","book":"04","title":"HYMN LIII. Indra, indra, Varuna, and Mitra, Soma, Maghavan, Savitar, Visnu.","link":"https://indra.ai/rigveda/hymns/04053.html","text":"p: OF @Indra, @Indra, @Varuna, and @Mitra, #Soma, @Maghavan, @Savitar, @Visnu the @Deva, the sapient #Asura, we crave this great #gift which is worthy of our choice, Wherewith he freely grants his worshiper defence. This with his rays the Great @Deva.hath vouchsafed to us.\n\np: Sustainer of the $Heaven, #Lord of the whole world's #life, the #Sage, he putteth on his golden-coloured mail. Clear-sighted, spreading far, filling the spacious realm, @Indra, @Indra, @Varuna, and @Mitra, #Soma, @Maghavan, @Savitar, @Visnu hath brought forth #bliss that deserveth laud.\n\np: He hath filled full the regions of the $Heaven and $Earth: the @Deva.for his own strengthening waketh up the #hymn. @Indra, @Indra, @Varuna, and @Mitra, #Soma, @Maghavan, @Savitar, @Visnu hath stretched out his arms to cherish #life, producing with his rays and lulling all that moves.\n\np: Lighting all living creatures, ne’er to be deceived, @Indra, @Indra, @Varuna, and @Mitra, #Soma, @Maghavan, @Savitar, @Visnu, @Deva, protects each holy ordinance. He hath stretched out his arms to all the folk of $Earth, and, with his laws observed, rules his own #mighty course.\n\np: @Indra, @Indra, @Varuna, and @Mitra, #Soma, @Maghavan, @Savitar, @Visnu thrice surrounding with his mightiness $$Mid-#Air, three regions, and the triple sphere of #light, Sets the three heavens in motion and the threefold $Earth, and willingly protects us with his triple law.\n\np: Most gracious @Deva, who brings to #life and lulls to rest, he who controls the world, what moves not and what moves, may he vouchsafe us shelter.@Indra, @Indra, @Varuna, and @Mitra, #Soma, @Maghavan, @Savitar, @Visnu the @Deva.for tranquil #life, with triple bar against distress.\n\np: With the year's #seasons hath @Indra, @Indra, @Varuna, and @Mitra, #Soma, @Maghavan, @Savitar, @Visnu, @Deva, come nigh. May he prosper our #home, give #food and noble #sons. May he invigorate us through the days and nights, an. May he send us opulence with #progeny.","people":["@Indra","@Visnu","@Mitra","@Varuna","@Maghavan","@Savitar","@Visnu","@Deva"],"places":["$Earth","$Heaven","$Mid-Air","$Mid-Air"],"things":["#Lord","#Seasons","#Soma","#Light","#Air","#Food","#Home","#Mighty","#Hymn","#Gift","#Bliss","#Sage","#Life"],"groups":["#Asura","#Sons","#Progeny"],"concepts":["Life","Holy","Noble"],"hash":"md5-mllqyckth3JCoWV7HaENJA==","created":"Wednesday, November 22, 2023 - 6:01:43 AM"},{"id":"b1af414b-52b3-4dab-ac69-bdec689fa24e","key":"04054","book":"04","title":"HYMN LIV. Indra, indra, Varuna, and Mitra, Soma, Maghavan, Savitar, Visnu.","link":"https://indra.ai/rigveda/hymns/04054.html","text":"p: Now must we #praise and honour @Indra, @Indra, @Varuna, and @Mitra, #Soma, @Maghavan, @Savitar: at this time of the day the #men must #call to himhim who distributes #wealth to Manu's #progeny, that h. May grant us here #riches most #excellent.\n\np: For thou at first producest for the holy #Devas the noblest of all portions, immortality: Thereafter as a #gift to #men, O @Indra, @Indra, @Varuna, and @Mitra, #Soma, @Maghavan, @Savitar, @Visnu, thou openest existence, #life succeeding #life.\n\np: If we, #men as we are, have sinned against the #Devas through want of thought, in weakness, or through insolence, Absolve us from the guilt and make us free from sin, O @Indra, @Indra, @Varuna, and @Mitra, #Soma, @Maghavan, @Savitar, @Visnu, alike among both #Devas and #men.\n\np: Non. May impede that power of @Indra, @Indra, @Varuna, and @Mitra, #Soma, @Maghavan, @Savitar whereby he will maintain the universal world. What the fair-fingered @Deva.brings forth on $Earth's expanse or in the height of $Heaven, that #work of his stands sure.\n\np: To lofty hills thou sendest those whom @Indra leads, and givest fixed abodes with houses unto these. However the, may fly and draw themselves apart, still, @Indra, @Indra, @Varuna, and @Mitra, #Soma, @Maghavan, @Savitar, @Visnu, they stand obeying thy behest.\n\np: May the #libations poured to thee thrice daily, day after day, O @Indra, @Indra, @Varuna, and @Mitra, #Soma, @Maghavan, @Savitar, @Visnu, bring us #blessing. May @Indra. $Heaven, $Earth, @Sindhu with the #Waters, @Aditi with @Adityas, give us shelter.","people":["@Indra","@Visnu","@Mitra","@Varuna","@Maghavan","@Adityas","@Adityas","@Savitar","@Visnu","@Deva","@Aditi","@Sindhu"],"places":["$Earth","$Heaven"],"things":["#Work","#Soma","#Waters","#Wealth","#Men","#Blessing","#Praise","#Gift","#Excellent","#Blessing","#Libations","#call","#Riches","#Life"],"groups":["#Devas","#Progeny"],"concepts":["Life","Immortality","Holy","Libations"],"hash":"md5-9bO0XLDa3/VbiKh213/DPw==","created":"Wednesday, November 22, 2023 - 6:01:43 AM"},{"id":"c2a6b3d2-a848-49fe-9a78-d3b1c38727d9","key":"04055","book":"04","title":"HYMN LV, Devas.","link":"https://indra.ai/rigveda/hymns/04055.html","text":"p: WHO of you, #Vasus, saveth? who protecteth? O $Heaven and $Earth and @Aditi, preserve us, @Varuna., @Mitra, from the stronger mortal. #Devas, which of you at #offering giveth comfort?\n\np: They who with laud extol the ancient statutes, when they #shine forth infallible dividers, have ordered as perpetual Ordainers, and beamed as holy-thoughted Wonder-Workers.\n\np: The Housewife Devi, @Aditi, and @Sindhu, the Devi Svasti I implore for friendship: An. May the unobstructed Night and #Morning both, day and night, provide for our protection.\n\np: @Aryaman, @Varuna have disclosed the pathway, @Agni as #Lord of Strength the road to welfare. Lauded in manly mod. May @Indra-@Visnu grant us their powerful defence and shelter.\n\np: I have besought the favour of the #Maruts, of Parvata, of @Bhaga @Deva who rescues. From trouble caused by #man the #Lord preserve us; from woe sent by his #friend let @Mitra save us.\n\np: Agree, through these our watery oblations, Devis. $Heaven and $Earth, with @Ahibudhnya. As if to win the sea, the Gharma-heaters have opened, as they come anear, the #rivers.\n\np: May Devi @Aditi with #Devas defend us, save us the saviour @Deva.with care unceasing. We dare not stint the sacred #food of @Mitra and @Varuna upon the back of @Agni.\n\np: @Agni is Sovran #Lord of #wealth, @Agni of great prosperity: May he bestow these #gifts on us.\n\np: Hither to us, rich pleasant @Dawn, bring many things to be desired, Thou who hast ample store of #wealth.\n\np: So the, may @Bhaga, @Indra, @Indra, @Varuna, and @Mitra, #Soma, @Maghavan, @Savitar, @Visnu, @Varuna, @Mitra, @Aryaman, @Indra, with bounty come to us.","people":["@Indra","@Agni","@Visnu","@Mitra","@Varuna","@Maghavan","@Savitar","@Visnu","@Bhaga","@Deva","@Dawn","@Aditi","@Sindhu","@Ahibudhnya","@Aryaman"],"places":["$Earth","$Heaven"],"things":["#Lord","#Rivers","#Soma","#Offering","#Shine","#Wealth","#Food","#Rivers","#Offering","#Friend","#Morning","#Gifts"],"groups":["#Devas","#Maruts","#Man","#Vasus"],"concepts":["Wonder-Workers","Friendship","Holy","Sacred","Strength","Offering","Powerful"],"hash":"md5-GJryCEWOuazPetKFFNGApA==","created":"Wednesday, November 22, 2023 - 6:01:43 AM"},{"id":"4cceef37-a687-450c-893b-6faca5a85d7a","key":"04056","book":"04","title":"HYMN LVI. Heaven and Earth.","link":"https://indra.ai/rigveda/hymns/04056.html","text":"p: MAY #mighty $Heaven and $Earth, most meet for honour, be present here with #light and gleaming splendours; When, fixing them apart, vast, most extensive, the Steer roars loudly in far-reaching courses.\n\np: The Devis with #Devas, holy with holy, the Two stand pouring out their #rain, exhaustless: Faithful and guileless, having #Devas for children, leaders of #offering with shining splendours.\n\np: Sure in the worlds he was a skilful Craftsman, he who produced these Twain the $Earth and $Heaven. #Wise, with his power he brought both realms, together spacious and deep, well-fashioned, unsupported.\n\np: O $Heaven and $Earth, with one accord promoting, with high protection as of Queens, our welfare, Far-reaching, universal, holy, guard us. May we, #car-borne, through #song be victors ever.\n\np: To both of you, O $Heaven and $Earth, we bring our lofty #song of #praise, pure Ones! to glorify you both.\n\np: Ye sanctify each other's #form, by your own proper #might ye rule, and from of old observe the Law.\n\np: Furthering and fulfilling, ye, O #Mighty, perfect @Mitra's Law. Ye sit around  'our #offering.","people":["@Mitra"],"places":["$Earth","$Heaven"],"things":["#Offering","#Light","#Might","#Rain","#Song","#Wise","#Mighty","#Car","#Praise","#Form","#Offering"],"groups":["#Devas"],"concepts":["Holy","Offering"],"hash":"md5-3eam4VHFLVMBnz31kaYW5w==","created":"Wednesday, November 22, 2023 - 6:01:43 AM"},{"id":"92c0b948-d604-42de-8949-31ab6fc94845","key":"04057","book":"04","title":"HYMN LVII. Ksetrapati, Etc.","link":"https://indra.ai/rigveda/hymns/04057.html","text":"p: WE through the #Master of the Field, even as through a #friend, obtain What nourisheth our kine and #steeds. In suc. May he be good to us.\n\np: As the #cow yieldeth #milk, pour for us freely, #Lord of the Field, the wave that beareth sweetness, Distilling #meath, well-purified like butter, and let the. Lords of holy Law be gracious.\n\np: Sweet be the plants for us. the heavens, the #waters, and full of sweets for us be #air's mid-region. May the Field's #Lord for us be full of sweetness, an. May we follow after him uninjured.\n\np: Happily #work our #steers and #men. May the plough furrow happily. Happily be the traces bound; happil. May he ply the goad.\n\np: Suna and Sira, welcome ye this laud, and with the #milk which ye have made in $Heaven Bedew ye both this $Earth of ours.\n\np: Auspicious Sita, come thou near: we venerate and #worship thee That tho. Mayst bless and prosper us and bring us fruits abundantly.\n\np: May @Indra press the furrow down. May @Pusan guide its course aright. May she, as rich in #milk, be drained for us through each succeeding year.\n\np: Happily let the shares turn up the plough-land, happily go the ploughers with the oxen. With #meath and #milk @Parjanya make us happy. Grant us prosperity, Suna and Sira.","people":["@Indra","@Pusan","@Parjanya"],"places":["$Earth","$Heaven"],"things":["#Worship","#Meath","#Master","#Milk","#Steeds","#Work","#Lord","#Waters","#Air","#Men","#Worship","#Friend","#Cow"],"groups":["#Steers"],"concepts":["Good","Holy","Auspicious"],"hash":"md5-A8pfZDnW//3tuMfwZMtofA==","created":"Wednesday, November 22, 2023 - 6:01:43 AM"},{"id":"355778b9-f7c1-4cd4-96b1-72be17f72e8f","key":"04058","book":"04","title":"HYMN LVIII. Ghrta.","link":"https://indra.ai/rigveda/hymns/04058.html","text":"p: FORTH from the $Ocean sprang the wave of sweetness: together with the stalk it turned to Amrta, that which is holy oil's mysterious title: but the #Devas’ tongue is truly Amrta's centre.\n\np: Let us declare aloud the name of Ghrta, and at this #offering hold it up with homage. So let the Brahman hear the #praise we utter. This hath the four-horned Buffalo emitted.\n\np: Four are his horns, three are the feet that bear him; his heads are two, his hands are seven in number. Bound with a triple bond the Steer roars loudly: the #mighty @Deva.hath entered in to mortals.\n\np: That oil in triple shape the #Devas discovered laid down within the #Cow, concealed by #Panis. @Indra produced one shape, @Surya another: by their own power they formed the third from Vena.\n\np: From inmost #reservoir in countless channels #flow down these #rivers which the foe beholds not. I look upon the #streams of oil descending, and lo! the Golden Reed is there among them.\n\np: Like #rivers our #libations #flow together, cleansing themselves in inmost heart and #spirit. The #streams of holy oil pour swiftly downward like the wild beasts that fly before the bowman.\n\np: As rushing down the rapids of a #river, #flow swifter than the wind the vigorous currents, the #streams of oil in swelling fluctuation like a red courser bursting through the fences.\n\np: Like women at a gathering fair to look on and gently smiling, they incline to @Agni. The #streams of holy oil attain the fuel, and #Jatavedas joyfully receives them.\n\np: As maidens dock themselves with gay adornment to join the #bridal feast, I now behold them. Where #Soma flows and #offering is ready, thither the #streams of holy oil are running.\n\np: Send to our eulogy a herd of #cattle bestow upon us #excellent possessions. Bear to the #Devas  'the #offering we offer the #streams of oil #flow pure and full of sweetness.\n\np: The universe depends upon thy power and #might within the sea, within the heart, within all #life.","people":["@Indra","@Agni","@Deva","@Surya"],"places":["$Ocean"],"things":["#Rivers","#Soma","#Offering","#Rivers","#River","#Streams","#Flow","#Might","#Mighty","#Reservoir","#Praise","#Excellent","#Offering","#Libations","#Cow","#Bridal","#Cattle","#Life","#Spirit"],"groups":["#Devas","#Jatavedas","#Panis"],"concepts":["Life","Holy","Offering","Libations"],"hash":"md5-neJ6gKchJOD31i/IKjbVUQ==","created":"Wednesday, November 22, 2023 - 6:01:43 AM"}],"copyright":"©2023 Quinn Michaels (indra.ai). All rights reserved.","created":"Wednesday, November 22, 2023 - 6:01:41 AM"}